03_Intermediate_Combinational/030_Basic_ALU/dataflow.v
module alu_4bit (

input [3:0] a,
input [3:0] b,
input [1:0] s,

output [3:0] out,
output carry,
output borrow

);

parameter ADD = 00,
          SUB = 01,
          AND = 10,
          OR  = 11;


wire [4:0] add, sub;

assign add = a + b;
assign sub = a - b;

assign out = (s == ADD) ? add[3:0]: 
             (s == SUB) ? sub[3:0]: 
             (s == AND) ? (a & b) :
             (a | b);

assign carry = (s == ADD) ? add[4] : 1'b0;
assign borrow = ( s == SUB) ? sub[4] : 1'b0;

endmodule

03_Intermediate_Combinational/030_Basic_ALU/tb_alu.v
module tb_alu_4bit;

reg [3:0] a;
reg [3:0] b;
reg [1:0] s;

wire [3:0] out;
wire carry;
wire borrow;

integer i;

alu_4bit DUT (.a(a), .b(b), .s(s), .out(out), .carry(carry), .borrow(borrow));


parameter ADD = 2'b00,
          SUB = 2'b01,
          AND = 2'b10,
          OR  = 2'b11;

  reg[23:0] Operation;


  always@ (*) begin
	  case(s)
		  ADD: Operation = "ADD";
		  SUB: Operation = "SUB";
		  AND: Operation = "AND";
		  OR : Operation = "OR ";

	  endcase
  end


initial begin

$dumpfile ("alu_4bit.vcd");
$dumpvars (0, tb_alu_4bit);

$monitor (" Time = %0t | Operation = %s | a = %b | b = %b | s = %b | out = %b | carry = %b | borrow = %b", $time, Operation, a, b, s, out, carry, borrow);

for (i = 0; i < 64; i = i +1) begin

a = i[3:0];
b = i[3:0];
s = i[1:0];

#10;

end

$finish;

end

endmodule

03_Intermediate_Combinational/030_Basic_ALU/alu_4bit.vcd
$date
	Wed Jul  1 06:09:13 2026
$end
$version
	Icarus Verilog
$end
$timescale
	1s
$end
$scope module tb_alu_4bit $end
$var wire 4 ! out [3:0] $end
$var wire 1 " carry $end
$var wire 1 # borrow $end
$var parameter 2 $ ADD $end
$var parameter 2 % AND $end
$var parameter 2 & OR $end
$var parameter 2 ' SUB $end
$var reg 24 ( Operation [23:0] $end
$var reg 4 ) a [3:0] $end
$var reg 4 * b [3:0] $end
$var reg 2 + s [1:0] $end
$var integer 32 , i [31:0] $end
$scope module DUT $end
$var wire 4 - a [3:0] $end
$var wire 4 . b [3:0] $end
$var wire 2 / s [1:0] $end
$var wire 5 0 sub [4:0] $end
$var wire 4 1 out [3:0] $end
$var wire 1 " carry $end
$var wire 1 # borrow $end
$var wire 5 2 add [4:0] $end
$var parameter 32 3 ADD $end
$var parameter 32 4 AND $end
$var parameter 32 5 OR $end
$var parameter 32 6 SUB $end
$upscope $end
$upscope $end
$enddefinitions $end
$comment Show the parameter values. $end
$dumpall
b1 6
b1011 5
b1010 4
b0 3
b1 '
b11 &
b10 %
b0 $
$end
#0
$dumpvars
b0 2
b0 1
b0 0
b0 /
b0 .
b0 -
b0 ,
b0 +
b0 *
b0 )
b10000010100010001000100 (
0#
0"
b0 !
$end
#10
b10100110101010101000010 (
b1 +
b1 /
b1 *
b1 .
b10 2
b0 0
b1 )
b1 -
b1 ,
#20
b10 !
b10 1
b10000010100111001000100 (
b10 +
b10 /
b10 *
b10 .
b100 2
b0 0
b10 )
b10 -
b10 ,
#30
b11 !
b11 1
b10011110101001000100000 (
b11 +
b11 /
b11 *
b11 .
b110 2
b0 0
b11 )
b11 -
b11 ,
#40
b1000 !
b1000 1
b10000010100010001000100 (
b0 +
b0 /
b100 *
b100 .
b1000 2
b0 0
b100 )
b100 -
b100 ,
#50
b0 !
b0 1
b10100110101010101000010 (
b1 +
b1 /
b101 *
b101 .
b1010 2
b0 0
b101 )
b101 -
b101 ,
#60
b110 !
b110 1
b10000010100111001000100 (
b10 +
b10 /
b110 *
b110 .
b1100 2
b0 0
b110 )
b110 -
b110 ,
#70
b111 !
b111 1
b10011110101001000100000 (
b11 +
b11 /
b111 *
b111 .
b1110 2
b0 0
b111 )
b111 -
b111 ,
#80
b0 !
b0 1
1"
b10000010100010001000100 (
b0 +
b0 /
b1000 *
b1000 .
b10000 2
b0 0
b1000 )
b1000 -
b1000 ,
#90
0"
b10100110101010101000010 (
b1 +
b1 /
b1001 *
b1001 .
b10010 2
b0 0
b1001 )
b1001 -
b1001 ,
#100
b1010 !
b1010 1
b10000010100111001000100 (
b10 +
b10 /
b1010 *
b1010 .
b10100 2
b0 0
b1010 )
b1010 -
b1010 ,
#110
b1011 !
b1011 1
b10011110101001000100000 (
b11 +
b11 /
b1011 *
b1011 .
b10110 2
b0 0
b1011 )
b1011 -
b1011 ,
#120
b1000 !
b1000 1
1"
b10000010100010001000100 (
b0 +
b0 /
b1100 *
b1100 .
b11000 2
b0 0
b1100 )
b1100 -
b1100 ,
#130
b0 !
b0 1
0"
b10100110101010101000010 (
b1 +
b1 /
b1101 *
b1101 .
b11010 2
b0 0
b1101 )
b1101 -
b1101 ,
#140
b1110 !
b1110 1
b10000010100111001000100 (
b10 +
b10 /
b1110 *
b1110 .
b11100 2
b0 0
b1110 )
b1110 -
b1110 ,
#150
b1111 !
b1111 1
b10011110101001000100000 (
b11 +
b11 /
b1111 *
b1111 .
b11110 2
b0 0
b1111 )
b1111 -
b1111 ,
#160
b0 !
b0 1
b10000010100010001000100 (
b0 +
b0 /
b0 *
b0 .
b0 2
b0 0
b0 )
b0 -
b10000 ,
#170
b10100110101010101000010 (
b1 +
b1 /
b1 *
b1 .
b10 2
b0 0
b1 )
b1 -
b10001 ,
#180
b10 !
b10 1
b10000010100111001000100 (
b10 +
b10 /
b10 *
b10 .
b100 2
b0 0
b10 )
b10 -
b10010 ,
#190
b11 !
b11 1
b10011110101001000100000 (
b11 +
b11 /
b11 *
b11 .
b110 2
b0 0
b11 )
b11 -
b10011 ,
#200
b1000 !
b1000 1
b10000010100010001000100 (
b0 +
b0 /
b100 *
b100 .
b1000 2
b0 0
b100 )
b100 -
b10100 ,
#210
b0 !
b0 1
b10100110101010101000010 (
b1 +
b1 /
b101 *
b101 .
b1010 2
b0 0
b101 )
b101 -
b10101 ,
#220
b110 !
b110 1
b10000010100111001000100 (
b10 +
b10 /
b110 *
b110 .
b1100 2
b0 0
b110 )
b110 -
b10110 ,
#230
b111 !
b111 1
b10011110101001000100000 (
b11 +
b11 /
b111 *
b111 .
b1110 2
b0 0
b111 )
b111 -
b10111 ,
#240
b0 !
b0 1
1"
b10000010100010001000100 (
b0 +
b0 /
b1000 *
b1000 .
b10000 2
b0 0
b1000 )
b1000 -
b11000 ,
#250
0"
b10100110101010101000010 (
b1 +
b1 /
b1001 *
b1001 .
b10010 2
b0 0
b1001 )
b1001 -
b11001 ,
#260
b1010 !
b1010 1
b10000010100111001000100 (
b10 +
b10 /
b1010 *
b1010 .
b10100 2
b0 0
b1010 )
b1010 -
b11010 ,
#270
b1011 !
b1011 1
b10011110101001000100000 (
b11 +
b11 /
b1011 *
b1011 .
b10110 2
b0 0
b1011 )
b1011 -
b11011 ,
#280
b1000 !
b1000 1
1"
b10000010100010001000100 (
b0 +
b0 /
b1100 *
b1100 .
b11000 2
b0 0
b1100 )
b1100 -
b11100 ,
#290
b0 !
b0 1
0"
b10100110101010101000010 (
b1 +
b1 /
b1101 *
b1101 .
b11010 2
b0 0
b1101 )
b1101 -
b11101 ,
#300
b1110 !
b1110 1
b10000010100111001000100 (
b10 +
b10 /
b1110 *
b1110 .
b11100 2
b0 0
b1110 )
b1110 -
b11110 ,
#310
b1111 !
b1111 1
b10011110101001000100000 (
b11 +
b11 /
b1111 *
b1111 .
b11110 2
b0 0
b1111 )
b1111 -
b11111 ,
#320
b0 !
b0 1
b10000010100010001000100 (
b0 +
b0 /
b0 *
b0 .
b0 2
b0 0
b0 )
b0 -
b100000 ,
#330
b10100110101010101000010 (
b1 +
b1 /
b1 *
b1 .
b10 2
b0 0
b1 )
b1 -
b100001 ,
#340
b10 !
b10 1
b10000010100111001000100 (
b10 +
b10 /
b10 *
b10 .
b100 2
b0 0
b10 )
b10 -
b100010 ,
#350
b11 !
b11 1
b10011110101001000100000 (
b11 +
b11 /
b11 *
b11 .
b110 2
b0 0
b11 )
b11 -
b100011 ,
#360
b1000 !
b1000 1
b10000010100010001000100 (
b0 +
b0 /
b100 *
b100 .
b1000 2
b0 0
b100 )
b100 -
b100100 ,
#370
b0 !
b0 1
b10100110101010101000010 (
b1 +
b1 /
b101 *
b101 .
b1010 2
b0 0
b101 )
b101 -
b100101 ,
#380
b110 !
b110 1
b10000010100111001000100 (
b10 +
b10 /
b110 *
b110 .
b1100 2
b0 0
b110 )
b110 -
b100110 ,
#390
b111 !
b111 1
b10011110101001000100000 (
b11 +
b11 /
b111 *
b111 .
b1110 2
b0 0
b111 )
b111 -
b100111 ,
#400
b0 !
b0 1
1"
b10000010100010001000100 (
b0 +
b0 /
b1000 *
b1000 .
b10000 2
b0 0
b1000 )
b1000 -
b101000 ,
#410
0"
b10100110101010101000010 (
b1 +
b1 /
b1001 *
b1001 .
b10010 2
b0 0
b1001 )
b1001 -
b101001 ,
#420
b1010 !
b1010 1
b10000010100111001000100 (
b10 +
b10 /
b1010 *
b1010 .
b10100 2
b0 0
b1010 )
b1010 -
b101010 ,
#430
b1011 !
b1011 1
b10011110101001000100000 (
b11 +
b11 /
b1011 *
b1011 .
b10110 2
b0 0
b1011 )
b1011 -
b101011 ,
#440
b1000 !
b1000 1
1"
b10000010100010001000100 (
b0 +
b0 /
b1100 *
b1100 .
b11000 2
b0 0
b1100 )
b1100 -
b101100 ,
#450
b0 !
b0 1
0"
b10100110101010101000010 (
b1 +
b1 /
b1101 *
b1101 .
b11010 2
b0 0
b1101 )
b1101 -
b101101 ,
#460
b1110 !
b1110 1
b10000010100111001000100 (
b10 +
b10 /
b1110 *
b1110 .
b11100 2
b0 0
b1110 )
b1110 -
b101110 ,
#470
b1111 !
b1111 1
b10011110101001000100000 (
b11 +
b11 /
b1111 *
b1111 .
b11110 2
b0 0
b1111 )
b1111 -
b101111 ,
#480
b0 !
b0 1
b10000010100010001000100 (
b0 +
b0 /
b0 *
b0 .
b0 2
b0 0
b0 )
b0 -
b110000 ,
#490
b10100110101010101000010 (
b1 +
b1 /
b1 *
b1 .
b10 2
b0 0
b1 )
b1 -
b110001 ,
#500
b10 !
b10 1
b10000010100111001000100 (
b10 +
b10 /
b10 *
b10 .
b100 2
b0 0
b10 )
b10 -
b110010 ,
#510
b11 !
b11 1
b10011110101001000100000 (
b11 +
b11 /
b11 *
b11 .
b110 2
b0 0
b11 )
b11 -
b110011 ,
#520
b1000 !
b1000 1
b10000010100010001000100 (
b0 +
b0 /
b100 *
b100 .
b1000 2
b0 0
b100 )
b100 -
b110100 ,
#530
b0 !
b0 1
b10100110101010101000010 (
b1 +
b1 /
b101 *
b101 .
b1010 2
b0 0
b101 )
b101 -
b110101 ,
#540
b110 !
b110 1
b10000010100111001000100 (
b10 +
b10 /
b110 *
b110 .
b1100 2
b0 0
b110 )
b110 -
b110110 ,
#550
b111 !
b111 1
b10011110101001000100000 (
b11 +
b11 /
b111 *
b111 .
b1110 2
b0 0
b111 )
b111 -
b110111 ,
#560
b0 !
b0 1
1"
b10000010100010001000100 (
b0 +
b0 /
b1000 *
b1000 .
b10000 2
b0 0
b1000 )
b1000 -
b111000 ,
#570
0"
b10100110101010101000010 (
b1 +
b1 /
b1001 *
b1001 .
b10010 2
b0 0
b1001 )
b1001 -
b111001 ,
#580
b1010 !
b1010 1
b10000010100111001000100 (
b10 +
b10 /
b1010 *
b1010 .
b10100 2
b0 0
b1010 )
b1010 -
b111010 ,
#590
b1011 !
b1011 1
b10011110101001000100000 (
b11 +
b11 /
b1011 *
b1011 .
b10110 2
b0 0
b1011 )
b1011 -
b111011 ,
#600
b1000 !
b1000 1
1"
b10000010100010001000100 (
b0 +
b0 /
b1100 *
b1100 .
b11000 2
b0 0
b1100 )
b1100 -
b111100 ,
#610
b0 !
b0 1
0"
b10100110101010101000010 (
b1 +
b1 /
b1101 *
b1101 .
b11010 2
b0 0
b1101 )
b1101 -
b111101 ,
#620
b1110 !
b1110 1
b10000010100111001000100 (
b10 +
b10 /
b1110 *
b1110 .
b11100 2
b0 0
b1110 )
b1110 -
b111110 ,
#630
b1111 !
b1111 1
b10011110101001000100000 (
b11 +
b11 /
b1111 *
b1111 .
b11110 2
b0 0
b1111 )
b1111 -
b111111 ,
#640
b1000000 ,
