09_Memory_Basics/078_ROM/behavioural.v
module ROM(

input [2:0] address,
output [3:0] data

);

reg [3:0] memory[0:7];

initial begin

        memory[0] = 4'b0001;
	memory[1] = 4'b0010;
	memory[2] = 4'b0011;
	memory[3] = 4'b0100;
	memory[4] = 4'b0101;
	memory[5] = 4'b0110;
	memory[6] = 4'b0111;
	memory[7] = 4'b1000;


end

assign data = memory[address];

endmodule

09_Memory_Basics/078_ROM/tb_rom.v
module tb_rom;

reg [2:0] address;
wire [3:0] data;

integer i;

ROM DUT(.address(address), .data(data));

initial begin

$dumpfile ("ROM.vcd");
$dumpvars (0, tb_rom);

$monitor (" Time = %0t | address = %b | data = %b", $time, address, data);

for (i = 0; i < 8; i = i + 1)
begin

address = i;
#10;

end

$finish;

end

endmodule

09_Memory_Basics/078_ROM/ROM.vcd
$date
	Mon Jul  6 06:53:11 2026
$end
$version
	Icarus Verilog
$end
$timescale
	1s
$end
$scope module tb_rom $end
$var wire 4 ! data [3:0] $end
$var reg 3 " address [2:0] $end
$var integer 32 # i [31:0] $end
$scope module DUT $end
$var wire 3 $ address [2:0] $end
$var wire 4 % data [3:0] $end
$upscope $end
$upscope $end
$enddefinitions $end
$comment Show the parameter values. $end
$dumpall
$end
#0
$dumpvars
b1 %
b0 $
b0 #
b0 "
b1 !
$end
#10
b10 !
b10 %
b1 "
b1 $
b1 #
#20
b11 !
b11 %
b10 "
b10 $
b10 #
#30
b100 !
b100 %
b11 "
b11 $
b11 #
#40
b101 !
b101 %
b100 "
b100 $
b100 #
#50
b110 !
b110 %
b101 "
b101 $
b101 #
#60
b111 !
b111 %
b110 "
b110 $
b110 #
#70
b1000 !
b1000 %
b111 "
b111 $
b111 #
#80
b1000 #
