06_Registers/051_8bit_Register/behavioural.v
module register_8bit (

input clk,
input rst,
input [7:0] d,

output reg[7:0] q

);

always @(posedge clk) begin

if (rst)

q <= 8'b00000000;

else

q <= d;

end

endmodule

06_Registers/051_8bit_Register/tb_register_8bit.v
module tb_register_8bit;

reg clk;
reg rst;
reg [7:0] d;

wire [7:0] q;

integer i;

register_8bit UUT(.clk(clk), .rst(rst), .d(d), .q(q));

initial clk = 0;
always #5 clk = ~clk;

always @(posedge clk or negedge clk) begin

if(clk)
$display ("Time = %0t: Rising Edge", $time);
else
$display ("Time = %0t: Falling Edge", $time);

end

initial begin

$dumpfile ("register_8bit.vcd");
$dumpvars (0, tb_register_8bit);

$monitor (" Time = %0t | cl = %b | rst = %b | d = %b | q = %b", $time, clk, rst, d, q);

#5;

rst =1;
d = 0;

rst = 0;

for (i = 0; i < 256; i = i + 1) begin

d = i;

#10;
end

$finish;

end

endmodule

06_Registers/051_8bit_Register/register_8bit.vcd
$date
	Thu Jul  2 11:11:21 2026
$end
$version
	Icarus Verilog
$end
$timescale
	1s
$end
$scope module tb_register_8bit $end
$var wire 8 ! q [7:0] $end
$var reg 1 " clk $end
$var reg 8 # d [7:0] $end
$var reg 1 $ rst $end
$var integer 32 % i [31:0] $end
$scope module UUT $end
$var wire 1 " clk $end
$var wire 8 & d [7:0] $end
$var wire 1 $ rst $end
$var reg 8 ' q [7:0] $end
$upscope $end
$upscope $end
$enddefinitions $end
$comment Show the parameter values. $end
$dumpall
$end
#0
$dumpvars
bx '
bx &
bx %
x$
bx #
0"
bx !
$end
#5
b0 !
b0 '
b0 %
b0 #
b0 &
0$
1"
#10
0"
#15
b1 !
b1 '
1"
b1 #
b1 &
b1 %
#20
0"
#25
b10 !
b10 '
1"
b10 #
b10 &
b10 %
#30
0"
#35
b11 !
b11 '
1"
b11 #
b11 &
b11 %
#40
0"
#45
b100 !
b100 '
1"
b100 #
b100 &
b100 %
#50
0"
#55
b101 !
b101 '
1"
b101 #
b101 &
b101 %
#60
0"
#65
b110 !
b110 '
1"
b110 #
b110 &
b110 %
#70
0"
#75
b111 !
b111 '
1"
b111 #
b111 &
b111 %
#80
0"
#85
b1000 !
b1000 '
1"
b1000 #
b1000 &
b1000 %
#90
0"
#95
b1001 !
b1001 '
1"
b1001 #
b1001 &
b1001 %
#100
0"
#105
b1010 !
b1010 '
1"
b1010 #
b1010 &
b1010 %
#110
0"
#115
b1011 !
b1011 '
1"
b1011 #
b1011 &
b1011 %
#120
0"
#125
b1100 !
b1100 '
1"
b1100 #
b1100 &
b1100 %
#130
0"
#135
b1101 !
b1101 '
1"
b1101 #
b1101 &
b1101 %
#140
0"
#145
b1110 !
b1110 '
1"
b1110 #
b1110 &
b1110 %
#150
0"
#155
b1111 !
b1111 '
1"
b1111 #
b1111 &
b1111 %
#160
0"
#165
b10000 !
b10000 '
1"
b10000 #
b10000 &
b10000 %
#170
0"
#175
b10001 !
b10001 '
1"
b10001 #
b10001 &
b10001 %
#180
0"
#185
b10010 !
b10010 '
1"
b10010 #
b10010 &
b10010 %
#190
0"
#195
b10011 !
b10011 '
1"
b10011 #
b10011 &
b10011 %
#200
0"
#205
b10100 !
b10100 '
1"
b10100 #
b10100 &
b10100 %
#210
0"
#215
b10101 !
b10101 '
1"
b10101 #
b10101 &
b10101 %
#220
0"
#225
b10110 !
b10110 '
1"
b10110 #
b10110 &
b10110 %
#230
0"
#235
b10111 !
b10111 '
1"
b10111 #
b10111 &
b10111 %
#240
0"
#245
b11000 !
b11000 '
1"
b11000 #
b11000 &
b11000 %
#250
0"
#255
b11001 !
b11001 '
1"
b11001 #
b11001 &
b11001 %
#260
0"
#265
b11010 !
b11010 '
1"
b11010 #
b11010 &
b11010 %
#270
0"
#275
b11011 !
b11011 '
1"
b11011 #
b11011 &
b11011 %
#280
0"
#285
b11100 !
b11100 '
1"
b11100 #
b11100 &
b11100 %
#290
0"
#295
b11101 !
b11101 '
1"
b11101 #
b11101 &
b11101 %
#300
0"
#305
b11110 !
b11110 '
1"
b11110 #
b11110 &
b11110 %
#310
0"
#315
b11111 !
b11111 '
1"
b11111 #
b11111 &
b11111 %
#320
0"
#325
b100000 !
b100000 '
1"
b100000 #
b100000 &
b100000 %
#330
0"
#335
b100001 !
b100001 '
1"
b100001 #
b100001 &
b100001 %
#340
0"
#345
b100010 !
b100010 '
1"
b100010 #
b100010 &
b100010 %
#350
0"
#355
b100011 !
b100011 '
1"
b100011 #
b100011 &
b100011 %
#360
0"
#365
b100100 !
b100100 '
1"
b100100 #
b100100 &
b100100 %
#370
0"
#375
b100101 !
b100101 '
1"
b100101 #
b100101 &
b100101 %
#380
0"
#385
b100110 !
b100110 '
1"
b100110 #
b100110 &
b100110 %
#390
0"
#395
b100111 !
b100111 '
1"
b100111 #
b100111 &
b100111 %
#400
0"
#405
b101000 !
b101000 '
1"
b101000 #
b101000 &
b101000 %
#410
0"
#415
b101001 !
b101001 '
1"
b101001 #
b101001 &
b101001 %
#420
0"
#425
b101010 !
b101010 '
1"
b101010 #
b101010 &
b101010 %
#430
0"
#435
b101011 !
b101011 '
1"
b101011 #
b101011 &
b101011 %
#440
0"
#445
b101100 !
b101100 '
1"
b101100 #
b101100 &
b101100 %
#450
0"
#455
b101101 !
b101101 '
1"
b101101 #
b101101 &
b101101 %
#460
0"
#465
b101110 !
b101110 '
1"
b101110 #
b101110 &
b101110 %
#470
0"
#475
b101111 !
b101111 '
1"
b101111 #
b101111 &
b101111 %
#480
0"
#485
b110000 !
b110000 '
1"
b110000 #
b110000 &
b110000 %
#490
0"
#495
b110001 !
b110001 '
1"
b110001 #
b110001 &
b110001 %
#500
0"
#505
b110010 !
b110010 '
1"
b110010 #
b110010 &
b110010 %
#510
0"
#515
b110011 !
b110011 '
1"
b110011 #
b110011 &
b110011 %
#520
0"
#525
b110100 !
b110100 '
1"
b110100 #
b110100 &
b110100 %
#530
0"
#535
b110101 !
b110101 '
1"
b110101 #
b110101 &
b110101 %
#540
0"
#545
b110110 !
b110110 '
1"
b110110 #
b110110 &
b110110 %
#550
0"
#555
b110111 !
b110111 '
1"
b110111 #
b110111 &
b110111 %
#560
0"
#565
b111000 !
b111000 '
1"
b111000 #
b111000 &
b111000 %
#570
0"
#575
b111001 !
b111001 '
1"
b111001 #
b111001 &
b111001 %
#580
0"
#585
b111010 !
b111010 '
1"
b111010 #
b111010 &
b111010 %
#590
0"
#595
b111011 !
b111011 '
1"
b111011 #
b111011 &
b111011 %
#600
0"
#605
b111100 !
b111100 '
1"
b111100 #
b111100 &
b111100 %
#610
0"
#615
b111101 !
b111101 '
1"
b111101 #
b111101 &
b111101 %
#620
0"
#625
b111110 !
b111110 '
1"
b111110 #
b111110 &
b111110 %
#630
0"
#635
b111111 !
b111111 '
1"
b111111 #
b111111 &
b111111 %
#640
0"
#645
b1000000 !
b1000000 '
1"
b1000000 #
b1000000 &
b1000000 %
#650
0"
#655
b1000001 !
b1000001 '
1"
b1000001 #
b1000001 &
b1000001 %
#660
0"
#665
b1000010 !
b1000010 '
1"
b1000010 #
b1000010 &
b1000010 %
#670
0"
#675
b1000011 !
b1000011 '
1"
b1000011 #
b1000011 &
b1000011 %
#680
0"
#685
b1000100 !
b1000100 '
1"
b1000100 #
b1000100 &
b1000100 %
#690
0"
#695
b1000101 !
b1000101 '
1"
b1000101 #
b1000101 &
b1000101 %
#700
0"
#705
b1000110 !
b1000110 '
1"
b1000110 #
b1000110 &
b1000110 %
#710
0"
#715
b1000111 !
b1000111 '
1"
b1000111 #
b1000111 &
b1000111 %
#720
0"
#725
b1001000 !
b1001000 '
1"
b1001000 #
b1001000 &
b1001000 %
#730
0"
#735
b1001001 !
b1001001 '
1"
b1001001 #
b1001001 &
b1001001 %
#740
0"
#745
b1001010 !
b1001010 '
1"
b1001010 #
b1001010 &
b1001010 %
#750
0"
#755
b1001011 !
b1001011 '
1"
b1001011 #
b1001011 &
b1001011 %
#760
0"
#765
b1001100 !
b1001100 '
1"
b1001100 #
b1001100 &
b1001100 %
#770
0"
#775
b1001101 !
b1001101 '
1"
b1001101 #
b1001101 &
b1001101 %
#780
0"
#785
b1001110 !
b1001110 '
1"
b1001110 #
b1001110 &
b1001110 %
#790
0"
#795
b1001111 !
b1001111 '
1"
b1001111 #
b1001111 &
b1001111 %
#800
0"
#805
b1010000 !
b1010000 '
1"
b1010000 #
b1010000 &
b1010000 %
#810
0"
#815
b1010001 !
b1010001 '
1"
b1010001 #
b1010001 &
b1010001 %
#820
0"
#825
b1010010 !
b1010010 '
1"
b1010010 #
b1010010 &
b1010010 %
#830
0"
#835
b1010011 !
b1010011 '
1"
b1010011 #
b1010011 &
b1010011 %
#840
0"
#845
b1010100 !
b1010100 '
1"
b1010100 #
b1010100 &
b1010100 %
#850
0"
#855
b1010101 !
b1010101 '
1"
b1010101 #
b1010101 &
b1010101 %
#860
0"
#865
b1010110 !
b1010110 '
1"
b1010110 #
b1010110 &
b1010110 %
#870
0"
#875
b1010111 !
b1010111 '
1"
b1010111 #
b1010111 &
b1010111 %
#880
0"
#885
b1011000 !
b1011000 '
1"
b1011000 #
b1011000 &
b1011000 %
#890
0"
#895
b1011001 !
b1011001 '
1"
b1011001 #
b1011001 &
b1011001 %
#900
0"
#905
b1011010 !
b1011010 '
1"
b1011010 #
b1011010 &
b1011010 %
#910
0"
#915
b1011011 !
b1011011 '
1"
b1011011 #
b1011011 &
b1011011 %
#920
0"
#925
b1011100 !
b1011100 '
1"
b1011100 #
b1011100 &
b1011100 %
#930
0"
#935
b1011101 !
b1011101 '
1"
b1011101 #
b1011101 &
b1011101 %
#940
0"
#945
b1011110 !
b1011110 '
1"
b1011110 #
b1011110 &
b1011110 %
#950
0"
#955
b1011111 !
b1011111 '
1"
b1011111 #
b1011111 &
b1011111 %
#960
0"
#965
b1100000 !
b1100000 '
1"
b1100000 #
b1100000 &
b1100000 %
#970
0"
#975
b1100001 !
b1100001 '
1"
b1100001 #
b1100001 &
b1100001 %
#980
0"
#985
b1100010 !
b1100010 '
1"
b1100010 #
b1100010 &
b1100010 %
#990
0"
#995
b1100011 !
b1100011 '
1"
b1100011 #
b1100011 &
b1100011 %
#1000
0"
#1005
b1100100 !
b1100100 '
1"
b1100100 #
b1100100 &
b1100100 %
#1010
0"
#1015
b1100101 !
b1100101 '
1"
b1100101 #
b1100101 &
b1100101 %
#1020
0"
#1025
b1100110 !
b1100110 '
1"
b1100110 #
b1100110 &
b1100110 %
#1030
0"
#1035
b1100111 !
b1100111 '
1"
b1100111 #
b1100111 &
b1100111 %
#1040
0"
#1045
b1101000 !
b1101000 '
1"
b1101000 #
b1101000 &
b1101000 %
#1050
0"
#1055
b1101001 !
b1101001 '
1"
b1101001 #
b1101001 &
b1101001 %
#1060
0"
#1065
b1101010 !
b1101010 '
1"
b1101010 #
b1101010 &
b1101010 %
#1070
0"
#1075
b1101011 !
b1101011 '
1"
b1101011 #
b1101011 &
b1101011 %
#1080
0"
#1085
b1101100 !
b1101100 '
1"
b1101100 #
b1101100 &
b1101100 %
#1090
0"
#1095
b1101101 !
b1101101 '
1"
b1101101 #
b1101101 &
b1101101 %
#1100
0"
#1105
b1101110 !
b1101110 '
1"
b1101110 #
b1101110 &
b1101110 %
#1110
0"
#1115
b1101111 !
b1101111 '
1"
b1101111 #
b1101111 &
b1101111 %
#1120
0"
#1125
b1110000 !
b1110000 '
1"
b1110000 #
b1110000 &
b1110000 %
#1130
0"
#1135
b1110001 !
b1110001 '
1"
b1110001 #
b1110001 &
b1110001 %
#1140
0"
#1145
b1110010 !
b1110010 '
1"
b1110010 #
b1110010 &
b1110010 %
#1150
0"
#1155
b1110011 !
b1110011 '
1"
b1110011 #
b1110011 &
b1110011 %
#1160
0"
#1165
b1110100 !
b1110100 '
1"
b1110100 #
b1110100 &
b1110100 %
#1170
0"
#1175
b1110101 !
b1110101 '
1"
b1110101 #
b1110101 &
b1110101 %
#1180
0"
#1185
b1110110 !
b1110110 '
1"
b1110110 #
b1110110 &
b1110110 %
#1190
0"
#1195
b1110111 !
b1110111 '
1"
b1110111 #
b1110111 &
b1110111 %
#1200
0"
#1205
b1111000 !
b1111000 '
1"
b1111000 #
b1111000 &
b1111000 %
#1210
0"
#1215
b1111001 !
b1111001 '
1"
b1111001 #
b1111001 &
b1111001 %
#1220
0"
#1225
b1111010 !
b1111010 '
1"
b1111010 #
b1111010 &
b1111010 %
#1230
0"
#1235
b1111011 !
b1111011 '
1"
b1111011 #
b1111011 &
b1111011 %
#1240
0"
#1245
b1111100 !
b1111100 '
1"
b1111100 #
b1111100 &
b1111100 %
#1250
0"
#1255
b1111101 !
b1111101 '
1"
b1111101 #
b1111101 &
b1111101 %
#1260
0"
#1265
b1111110 !
b1111110 '
1"
b1111110 #
b1111110 &
b1111110 %
#1270
0"
#1275
b1111111 !
b1111111 '
1"
b1111111 #
b1111111 &
b1111111 %
#1280
0"
#1285
b10000000 !
b10000000 '
1"
b10000000 #
b10000000 &
b10000000 %
#1290
0"
#1295
b10000001 !
b10000001 '
1"
b10000001 #
b10000001 &
b10000001 %
#1300
0"
#1305
b10000010 !
b10000010 '
1"
b10000010 #
b10000010 &
b10000010 %
#1310
0"
#1315
b10000011 !
b10000011 '
1"
b10000011 #
b10000011 &
b10000011 %
#1320
0"
#1325
b10000100 !
b10000100 '
1"
b10000100 #
b10000100 &
b10000100 %
#1330
0"
#1335
b10000101 !
b10000101 '
1"
b10000101 #
b10000101 &
b10000101 %
#1340
0"
#1345
b10000110 !
b10000110 '
1"
b10000110 #
b10000110 &
b10000110 %
#1350
0"
#1355
b10000111 !
b10000111 '
1"
b10000111 #
b10000111 &
b10000111 %
#1360
0"
#1365
b10001000 !
b10001000 '
1"
b10001000 #
b10001000 &
b10001000 %
#1370
0"
#1375
b10001001 !
b10001001 '
1"
b10001001 #
b10001001 &
b10001001 %
#1380
0"
#1385
b10001010 !
b10001010 '
1"
b10001010 #
b10001010 &
b10001010 %
#1390
0"
#1395
b10001011 !
b10001011 '
1"
b10001011 #
b10001011 &
b10001011 %
#1400
0"
#1405
b10001100 !
b10001100 '
1"
b10001100 #
b10001100 &
b10001100 %
#1410
0"
#1415
b10001101 !
b10001101 '
1"
b10001101 #
b10001101 &
b10001101 %
#1420
0"
#1425
b10001110 !
b10001110 '
1"
b10001110 #
b10001110 &
b10001110 %
#1430
0"
#1435
b10001111 !
b10001111 '
1"
b10001111 #
b10001111 &
b10001111 %
#1440
0"
#1445
b10010000 !
b10010000 '
1"
b10010000 #
b10010000 &
b10010000 %
#1450
0"
#1455
b10010001 !
b10010001 '
1"
b10010001 #
b10010001 &
b10010001 %
#1460
0"
#1465
b10010010 !
b10010010 '
1"
b10010010 #
b10010010 &
b10010010 %
#1470
0"
#1475
b10010011 !
b10010011 '
1"
b10010011 #
b10010011 &
b10010011 %
#1480
0"
#1485
b10010100 !
b10010100 '
1"
b10010100 #
b10010100 &
b10010100 %
#1490
0"
#1495
b10010101 !
b10010101 '
1"
b10010101 #
b10010101 &
b10010101 %
#1500
0"
#1505
b10010110 !
b10010110 '
1"
b10010110 #
b10010110 &
b10010110 %
#1510
0"
#1515
b10010111 !
b10010111 '
1"
b10010111 #
b10010111 &
b10010111 %
#1520
0"
#1525
b10011000 !
b10011000 '
1"
b10011000 #
b10011000 &
b10011000 %
#1530
0"
#1535
b10011001 !
b10011001 '
1"
b10011001 #
b10011001 &
b10011001 %
#1540
0"
#1545
b10011010 !
b10011010 '
1"
b10011010 #
b10011010 &
b10011010 %
#1550
0"
#1555
b10011011 !
b10011011 '
1"
b10011011 #
b10011011 &
b10011011 %
#1560
0"
#1565
b10011100 !
b10011100 '
1"
b10011100 #
b10011100 &
b10011100 %
#1570
0"
#1575
b10011101 !
b10011101 '
1"
b10011101 #
b10011101 &
b10011101 %
#1580
0"
#1585
b10011110 !
b10011110 '
1"
b10011110 #
b10011110 &
b10011110 %
#1590
0"
#1595
b10011111 !
b10011111 '
1"
b10011111 #
b10011111 &
b10011111 %
#1600
0"
#1605
b10100000 !
b10100000 '
1"
b10100000 #
b10100000 &
b10100000 %
#1610
0"
#1615
b10100001 !
b10100001 '
1"
b10100001 #
b10100001 &
b10100001 %
#1620
0"
#1625
b10100010 !
b10100010 '
1"
b10100010 #
b10100010 &
b10100010 %
#1630
0"
#1635
b10100011 !
b10100011 '
1"
b10100011 #
b10100011 &
b10100011 %
#1640
0"
#1645
b10100100 !
b10100100 '
1"
b10100100 #
b10100100 &
b10100100 %
#1650
0"
#1655
b10100101 !
b10100101 '
1"
b10100101 #
b10100101 &
b10100101 %
#1660
0"
#1665
b10100110 !
b10100110 '
1"
b10100110 #
b10100110 &
b10100110 %
#1670
0"
#1675
b10100111 !
b10100111 '
1"
b10100111 #
b10100111 &
b10100111 %
#1680
0"
#1685
b10101000 !
b10101000 '
1"
b10101000 #
b10101000 &
b10101000 %
#1690
0"
#1695
b10101001 !
b10101001 '
1"
b10101001 #
b10101001 &
b10101001 %
#1700
0"
#1705
b10101010 !
b10101010 '
1"
b10101010 #
b10101010 &
b10101010 %
#1710
0"
#1715
b10101011 !
b10101011 '
1"
b10101011 #
b10101011 &
b10101011 %
#1720
0"
#1725
b10101100 !
b10101100 '
1"
b10101100 #
b10101100 &
b10101100 %
#1730
0"
#1735
b10101101 !
b10101101 '
1"
b10101101 #
b10101101 &
b10101101 %
#1740
0"
#1745
b10101110 !
b10101110 '
1"
b10101110 #
b10101110 &
b10101110 %
#1750
0"
#1755
b10101111 !
b10101111 '
1"
b10101111 #
b10101111 &
b10101111 %
#1760
0"
#1765
b10110000 !
b10110000 '
1"
b10110000 #
b10110000 &
b10110000 %
#1770
0"
#1775
b10110001 !
b10110001 '
1"
b10110001 #
b10110001 &
b10110001 %
#1780
0"
#1785
b10110010 !
b10110010 '
1"
b10110010 #
b10110010 &
b10110010 %
#1790
0"
#1795
b10110011 !
b10110011 '
1"
b10110011 #
b10110011 &
b10110011 %
#1800
0"
#1805
b10110100 !
b10110100 '
1"
b10110100 #
b10110100 &
b10110100 %
#1810
0"
#1815
b10110101 !
b10110101 '
1"
b10110101 #
b10110101 &
b10110101 %
#1820
0"
#1825
b10110110 !
b10110110 '
1"
b10110110 #
b10110110 &
b10110110 %
#1830
0"
#1835
b10110111 !
b10110111 '
1"
b10110111 #
b10110111 &
b10110111 %
#1840
0"
#1845
b10111000 !
b10111000 '
1"
b10111000 #
b10111000 &
b10111000 %
#1850
0"
#1855
b10111001 !
b10111001 '
1"
b10111001 #
b10111001 &
b10111001 %
#1860
0"
#1865
b10111010 !
b10111010 '
1"
b10111010 #
b10111010 &
b10111010 %
#1870
0"
#1875
b10111011 !
b10111011 '
1"
b10111011 #
b10111011 &
b10111011 %
#1880
0"
#1885
b10111100 !
b10111100 '
1"
b10111100 #
b10111100 &
b10111100 %
#1890
0"
#1895
b10111101 !
b10111101 '
1"
b10111101 #
b10111101 &
b10111101 %
#1900
0"
#1905
b10111110 !
b10111110 '
1"
b10111110 #
b10111110 &
b10111110 %
#1910
0"
#1915
b10111111 !
b10111111 '
1"
b10111111 #
b10111111 &
b10111111 %
#1920
0"
#1925
b11000000 !
b11000000 '
1"
b11000000 #
b11000000 &
b11000000 %
#1930
0"
#1935
b11000001 !
b11000001 '
1"
b11000001 #
b11000001 &
b11000001 %
#1940
0"
#1945
b11000010 !
b11000010 '
1"
b11000010 #
b11000010 &
b11000010 %
#1950
0"
#1955
b11000011 !
b11000011 '
1"
b11000011 #
b11000011 &
b11000011 %
#1960
0"
#1965
b11000100 !
b11000100 '
1"
b11000100 #
b11000100 &
b11000100 %
#1970
0"
#1975
b11000101 !
b11000101 '
1"
b11000101 #
b11000101 &
b11000101 %
#1980
0"
#1985
b11000110 !
b11000110 '
1"
b11000110 #
b11000110 &
b11000110 %
#1990
0"
#1995
b11000111 !
b11000111 '
1"
b11000111 #
b11000111 &
b11000111 %
#2000
0"
#2005
b11001000 !
b11001000 '
1"
b11001000 #
b11001000 &
b11001000 %
#2010
0"
#2015
b11001001 !
b11001001 '
1"
b11001001 #
b11001001 &
b11001001 %
#2020
0"
#2025
b11001010 !
b11001010 '
1"
b11001010 #
b11001010 &
b11001010 %
#2030
0"
#2035
b11001011 !
b11001011 '
1"
b11001011 #
b11001011 &
b11001011 %
#2040
0"
#2045
b11001100 !
b11001100 '
1"
b11001100 #
b11001100 &
b11001100 %
#2050
0"
#2055
b11001101 !
b11001101 '
1"
b11001101 #
b11001101 &
b11001101 %
#2060
0"
#2065
b11001110 !
b11001110 '
1"
b11001110 #
b11001110 &
b11001110 %
#2070
0"
#2075
b11001111 !
b11001111 '
1"
b11001111 #
b11001111 &
b11001111 %
#2080
0"
#2085
b11010000 !
b11010000 '
1"
b11010000 #
b11010000 &
b11010000 %
#2090
0"
#2095
b11010001 !
b11010001 '
1"
b11010001 #
b11010001 &
b11010001 %
#2100
0"
#2105
b11010010 !
b11010010 '
1"
b11010010 #
b11010010 &
b11010010 %
#2110
0"
#2115
b11010011 !
b11010011 '
1"
b11010011 #
b11010011 &
b11010011 %
#2120
0"
#2125
b11010100 !
b11010100 '
1"
b11010100 #
b11010100 &
b11010100 %
#2130
0"
#2135
b11010101 !
b11010101 '
1"
b11010101 #
b11010101 &
b11010101 %
#2140
0"
#2145
b11010110 !
b11010110 '
1"
b11010110 #
b11010110 &
b11010110 %
#2150
0"
#2155
b11010111 !
b11010111 '
1"
b11010111 #
b11010111 &
b11010111 %
#2160
0"
#2165
b11011000 !
b11011000 '
1"
b11011000 #
b11011000 &
b11011000 %
#2170
0"
#2175
b11011001 !
b11011001 '
1"
b11011001 #
b11011001 &
b11011001 %
#2180
0"
#2185
b11011010 !
b11011010 '
1"
b11011010 #
b11011010 &
b11011010 %
#2190
0"
#2195
b11011011 !
b11011011 '
1"
b11011011 #
b11011011 &
b11011011 %
#2200
0"
#2205
b11011100 !
b11011100 '
1"
b11011100 #
b11011100 &
b11011100 %
#2210
0"
#2215
b11011101 !
b11011101 '
1"
b11011101 #
b11011101 &
b11011101 %
#2220
0"
#2225
b11011110 !
b11011110 '
1"
b11011110 #
b11011110 &
b11011110 %
#2230
0"
#2235
b11011111 !
b11011111 '
1"
b11011111 #
b11011111 &
b11011111 %
#2240
0"
#2245
b11100000 !
b11100000 '
1"
b11100000 #
b11100000 &
b11100000 %
#2250
0"
#2255
b11100001 !
b11100001 '
1"
b11100001 #
b11100001 &
b11100001 %
#2260
0"
#2265
b11100010 !
b11100010 '
1"
b11100010 #
b11100010 &
b11100010 %
#2270
0"
#2275
b11100011 !
b11100011 '
1"
b11100011 #
b11100011 &
b11100011 %
#2280
0"
#2285
b11100100 !
b11100100 '
1"
b11100100 #
b11100100 &
b11100100 %
#2290
0"
#2295
b11100101 !
b11100101 '
1"
b11100101 #
b11100101 &
b11100101 %
#2300
0"
#2305
b11100110 !
b11100110 '
1"
b11100110 #
b11100110 &
b11100110 %
#2310
0"
#2315
b11100111 !
b11100111 '
1"
b11100111 #
b11100111 &
b11100111 %
#2320
0"
#2325
b11101000 !
b11101000 '
1"
b11101000 #
b11101000 &
b11101000 %
#2330
0"
#2335
b11101001 !
b11101001 '
1"
b11101001 #
b11101001 &
b11101001 %
#2340
0"
#2345
b11101010 !
b11101010 '
1"
b11101010 #
b11101010 &
b11101010 %
#2350
0"
#2355
b11101011 !
b11101011 '
1"
b11101011 #
b11101011 &
b11101011 %
#2360
0"
#2365
b11101100 !
b11101100 '
1"
b11101100 #
b11101100 &
b11101100 %
#2370
0"
#2375
b11101101 !
b11101101 '
1"
b11101101 #
b11101101 &
b11101101 %
#2380
0"
#2385
b11101110 !
b11101110 '
1"
b11101110 #
b11101110 &
b11101110 %
#2390
0"
#2395
b11101111 !
b11101111 '
1"
b11101111 #
b11101111 &
b11101111 %
#2400
0"
#2405
b11110000 !
b11110000 '
1"
b11110000 #
b11110000 &
b11110000 %
#2410
0"
#2415
b11110001 !
b11110001 '
1"
b11110001 #
b11110001 &
b11110001 %
#2420
0"
#2425
b11110010 !
b11110010 '
1"
b11110010 #
b11110010 &
b11110010 %
#2430
0"
#2435
b11110011 !
b11110011 '
1"
b11110011 #
b11110011 &
b11110011 %
#2440
0"
#2445
b11110100 !
b11110100 '
1"
b11110100 #
b11110100 &
b11110100 %
#2450
0"
#2455
b11110101 !
b11110101 '
1"
b11110101 #
b11110101 &
b11110101 %
#2460
0"
#2465
b11110110 !
b11110110 '
1"
b11110110 #
b11110110 &
b11110110 %
#2470
0"
#2475
b11110111 !
b11110111 '
1"
b11110111 #
b11110111 &
b11110111 %
#2480
0"
#2485
b11111000 !
b11111000 '
1"
b11111000 #
b11111000 &
b11111000 %
#2490
0"
#2495
b11111001 !
b11111001 '
1"
b11111001 #
b11111001 &
b11111001 %
#2500
0"
#2505
b11111010 !
b11111010 '
1"
b11111010 #
b11111010 &
b11111010 %
#2510
0"
#2515
b11111011 !
b11111011 '
1"
b11111011 #
b11111011 &
b11111011 %
#2520
0"
#2525
b11111100 !
b11111100 '
1"
b11111100 #
b11111100 &
b11111100 %
#2530
0"
#2535
b11111101 !
b11111101 '
1"
b11111101 #
b11111101 &
b11111101 %
#2540
0"
#2545
b11111110 !
b11111110 '
1"
b11111110 #
b11111110 &
b11111110 %
#2550
0"
#2555
b11111111 !
b11111111 '
1"
b11111111 #
b11111111 &
b11111111 %
#2560
0"
#2565
1"
b100000000 %
