02_Basic_Combinational/011_Full_Subtractor/dataflow.v
module full_subtractor (

input a, b, cin,
output D, B0

);

assign D = a ^ b ^ cin;
assign B0 = ((!a & b) | ((a ^ b) & cin));

endmodule

02_Basic_Combinational/011_Full_Subtractor/tb_full_subtractor.v
module tb_full_subtractor;

reg a, b, cin;
wire D, B0;

integer i;

full_subtractor DUT (.a(a), .b(b), .cin(cin), .D(D), .B0(B0));

initial begin

$dumpfile ("full_subtractor.vcd");
$dumpvars (0, tb_full_subtractor);

$display ("--------------Full Subtractor-----------------");

$monitor ("Time = %0t | a = %b | b = %b | cin = %b | D = %b | B0 = %b", $time, a, b, cin, D, B0);

for(i = 0; i < 8; i = i+1)

begin 

{a, b, cin} = i;
#10;

end 

$finish;

end

endmodule

02_Basic_Combinational/011_Full_Subtractor/full_subtractor.vcd
$date
	Thu Jun 25 12:05:12 2026
$end
$version
	Icarus Verilog
$end
$timescale
	1s
$end
$scope module tb_full_subtractor $end
$var wire 1 ! D $end
$var wire 1 " B0 $end
$var reg 1 # a $end
$var reg 1 $ b $end
$var reg 1 % cin $end
$var integer 32 & i [31:0] $end
$scope module DUT $end
$var wire 1 # a $end
$var wire 1 $ b $end
$var wire 1 % cin $end
$var reg 1 " B0 $end
$var reg 1 ! D $end
$upscope $end
$upscope $end
$enddefinitions $end
$comment Show the parameter values. $end
$dumpall
$end
#0
$dumpvars
b0 &
0%
0$
0#
0"
0!
$end
#10
1"
1!
1%
b1 &
#20
1$
0%
b10 &
#30
0!
1%
b11 &
#40
0"
1!
1#
0$
0%
b100 &
#50
0!
1%
b101 &
#60
1$
0%
b110 &
#70
1"
1!
1%
b111 &
#80
b1000 &
