02_Basic_Combinational/015_1to4_DEMUX/dataflow.v
module demux_1to4 (

input a,
input s1,
input s2,
output w,
output x,
output y,
output z

);

assign w = (!s1 & !s2 & a);
assign x = (!s1 & s2 & a);
assign y = (s1 & !s2 & a);
assign z = (s1 & s2 & a);

endmodule

02_Basic_Combinational/015_1to4_DEMUX/tb_1to4_DEMUX.v
module tb_demux_1to4;

reg a;
reg s1;
reg s2;

wire w;
wire x;
wire y;
wire z;

integer i;

demux_1to4 DUT (.a(a), .s1(s1), .s2(s2), .w(w), .x(x), .y(y), .z(z));

initial begin

$dumpfile ("demux_1to4.vcd");
$dumpvars (0, tb_demux_1to4);

$monitor ("Time = %0t | a = %b | s1 = %b | s2 = %b | w = %b | x = %b | y = %b | z = %b", $time, a, s1, s2, w, x, y, z);

for (i = 0; i < 8; i = i+1)

begin

{s1, s2, a} = i;
#10;

end 

$finish;

end 

endmodule

02_Basic_Combinational/015_1to4_DEMUX/demux_1to4.vcd
$date
	Fri Jun 26 14:51:24 2026
$end
$version
	Icarus Verilog
$end
$timescale
	1s
$end
$scope module tb_demux_1to4 $end
$var wire 1 ! z $end
$var wire 1 " y $end
$var wire 1 # x $end
$var wire 1 $ w $end
$var reg 1 % a $end
$var reg 1 & s1 $end
$var reg 1 ' s2 $end
$var integer 32 ( i [31:0] $end
$scope module DUT $end
$var wire 1 % a $end
$var wire 1 & s1 $end
$var wire 1 ' s2 $end
$var reg 1 $ w $end
$var reg 1 # x $end
$var reg 1 " y $end
$var reg 1 ! z $end
$upscope $end
$upscope $end
$enddefinitions $end
$comment Show the parameter values. $end
$dumpall
$end
#0
$dumpvars
b0 (
0'
0&
0%
0$
0#
0"
0!
$end
#10
1$
1%
b1 (
#20
0$
1'
0%
b10 (
#30
1#
1%
b11 (
#40
0#
1&
0'
0%
b100 (
#50
1"
1%
b101 (
#60
0"
1'
0%
b110 (
#70
1!
1%
b111 (
#80
b1000 (
