07_Counters/067_Asynchronous_Counter/behavioural.v
module asynchronous_counter (

input clk,
input rst,

output [3:0] count

);

reg q0, q1, q2, q3;

always @(posedge clk or posedge rst) begin

if (rst)
q0 = 1'b0;
else 
q0 = ~q0;

end

always @(posedge q0 or posedge rst) begin

if(rst)
q1 = 1'b0;
else
q1 = ~q1;

end

always @(posedge q1 or posedge rst) begin

if(rst)
q2 = 1'b0;
else
q2 = ~q2;

end

always @(posedge q2 or posedge rst) begin

if (rst)
q3 = 1'b0;
else
q3 = ~q3;

end

assign count = {q0, q1, q2, q3};

endmodule

07_Counters/067_Asynchronous_Counter/tb_asynchronous_counter.v
module tb_asynchronous_counter;

reg clk;
reg rst;

wire [3:0] count;

asynchronous_counter DUT(.clk(clk), .rst(rst), .count(count));

initial clk = 0;
always #5 clk = ~clk;

always @(posedge clk or negedge clk) begin

    if(clk)
        $display("\nTime = %0t : Rising Edge",$time);
    else
        $display("Time = %0t : Falling Edge",$time);

end

initial begin

    $dumpfile("asynchronous_counter.vcd");
    $dumpvars(0, tb_asynchronous_counter);

    $monitor("Time = %0t | clk = %b | rst = %b | count = %0d (%b)",
              $time,clk,rst,count,count);

    rst = 1;

    #10;
    rst = 0;

    #180;

    $finish;

end

endmodule

07_Counters/067_Asynchronous_Counter/asynchronous_counter.vcd
$date
	Sat Jul  4 08:20:10 2026
$end
$version
	Icarus Verilog
$end
$timescale
	1s
$end
$scope module tb_asynchronous_counter $end
$var wire 4 ! count [3:0] $end
$var reg 1 " clk $end
$var reg 1 # rst $end
$scope module DUT $end
$var wire 1 " clk $end
$var wire 1 # rst $end
$var wire 4 $ count [3:0] $end
$var reg 1 % q0 $end
$var reg 1 & q1 $end
$var reg 1 ' q2 $end
$var reg 1 ( q3 $end
$upscope $end
$upscope $end
$enddefinitions $end
$comment Show the parameter values. $end
$dumpall
$end
#0
$dumpvars
0(
0'
0&
0%
b0 $
1#
0"
b0 !
$end
#5
1"
#10
0"
0#
#15
1(
1'
1&
b1111 !
b1111 $
1%
1"
#20
0"
#25
b111 !
b111 $
0%
1"
#30
0"
#35
0&
b1011 !
b1011 $
1%
1"
#40
0"
#45
b11 !
b11 $
0%
1"
#50
0"
#55
0'
1&
b1101 !
b1101 $
1%
1"
#60
0"
#65
b101 !
b101 $
0%
1"
#70
0"
#75
0&
b1001 !
b1001 $
1%
1"
#80
0"
#85
b1 !
b1 $
0%
1"
#90
0"
#95
0(
1'
1&
b1110 !
b1110 $
1%
1"
#100
0"
#105
b110 !
b110 $
0%
1"
#110
0"
#115
0&
b1010 !
b1010 $
1%
1"
#120
0"
#125
b10 !
b10 $
0%
1"
#130
0"
#135
0'
1&
b1100 !
b1100 $
1%
1"
#140
0"
#145
b100 !
b100 $
0%
1"
#150
0"
#155
0&
b1000 !
b1000 $
1%
1"
#160
0"
#165
b0 !
b0 $
0%
1"
#170
0"
#175
1(
1'
1&
b1111 !
b1111 $
1%
1"
#180
0"
#185
b111 !
b111 $
0%
1"
