03_Intermediate_Combinational/021_Comparator_4bit/behavioural.v
module comparator_4bit (

input [3:0] a,
input [3:0] b,

output reg a_equal_b,
output reg a_less_b,
output reg a_greater_b

);

//integer i;

//reg [7:0] a1, b1;

always@ (*) begin

	//a = b1;
        //b = b1;

	a_equal_b = 0;
	a_less_b = 0;
	a_greater_b = 0;

	//for (i = 0; i < 256; i = i + 1) begin

if (a == b) 
a_equal_b = 1;

else if (a < b) 
a_less_b = 1;

else if (a > b)
a_greater_b = 1;

#10;

end 

endmodule

03_Intermediate_Combinational/021_Comparator_4bit/tb_comparator_4bit.v
module tb_comparator_4bit;

reg [3:0] a;
reg [3:0] b;

wire a_equal_b;
wire a_less_b;
wire a_greater_b;

integer i;


comparator_4bit DUT (.a(a), .b(b), .a_equal_b(a_equal_b), .a_less_b(a_less_b), .a_greater_b(a_greater_b));

initial begin 

$dumpfile ("comparator_4bit.vcd");
$dumpvars (0, tb_comparator_4bit);

$monitor ("Time = %0t | a = %b | b = %b | a_equal_b = %b | a_less_b = %b | a_greater_b = %b", $time, a, b, a_equal_b, a_less_b, a_greater_b);

a = 0;
b = 0;

#5;

for (i = 0; i < 256; i = i + 1)

begin

/*a = i[7:4];
b = i[3:0];*/

{a, b} = i;

#10;

end

$finish;

end

endmodule

03_Intermediate_Combinational/021_Comparator_4bit/comparator_4bit.vcd
$date
	Tue Jun 30 07:34:42 2026
$end
$version
	Icarus Verilog
$end
$timescale
	1s
$end
$scope module tb_comparator_4bit $end
$var wire 1 ! a_less_b $end
$var wire 1 " a_greater_b $end
$var wire 1 # a_equal_b $end
$var reg 4 $ a [3:0] $end
$var reg 4 % b [3:0] $end
$var integer 32 & i [31:0] $end
$scope module DUT $end
$var wire 4 ' a [3:0] $end
$var wire 4 ( b [3:0] $end
$var reg 1 # a_equal_b $end
$var reg 1 " a_greater_b $end
$var reg 1 ! a_less_b $end
$upscope $end
$upscope $end
$enddefinitions $end
$comment Show the parameter values. $end
$dumpall
$end
#0
$dumpvars
b0 (
b0 '
bx &
b0 %
b0 $
1#
0"
0!
$end
#5
b0 &
#15
1!
0#
b1 %
b1 (
b1 &
#25
b10 %
b10 (
b10 &
#35
1!
b11 %
b11 (
b11 &
#45
b100 %
b100 (
b100 &
#55
1!
b101 %
b101 (
b101 &
#65
b110 %
b110 (
b110 &
#75
1!
b111 %
b111 (
b111 &
#85
b1000 %
b1000 (
b1000 &
#95
1!
b1001 %
b1001 (
b1001 &
#105
b1010 %
b1010 (
b1010 &
#115
1!
b1011 %
b1011 (
b1011 &
#125
b1100 %
b1100 (
b1100 &
#135
1!
b1101 %
b1101 (
b1101 &
#145
b1110 %
b1110 (
b1110 &
#155
1!
b1111 %
b1111 (
b1111 &
#165
b1 $
b1 '
b0 %
b0 (
b10000 &
#175
1#
0!
b1 %
b1 (
b10001 &
#185
b10 %
b10 (
b10010 &
#195
1!
0#
b11 %
b11 (
b10011 &
#205
b100 %
b100 (
b10100 &
#215
1!
b101 %
b101 (
b10101 &
#225
b110 %
b110 (
b10110 &
#235
1!
b111 %
b111 (
b10111 &
#245
b1000 %
b1000 (
b11000 &
#255
1!
b1001 %
b1001 (
b11001 &
#265
b1010 %
b1010 (
b11010 &
#275
1!
b1011 %
b1011 (
b11011 &
#285
b1100 %
b1100 (
b11100 &
#295
1!
b1101 %
b1101 (
b11101 &
#305
b1110 %
b1110 (
b11110 &
#315
1!
b1111 %
b1111 (
b11111 &
#325
b10 $
b10 '
b0 %
b0 (
b100000 &
#335
1"
0!
b1 %
b1 (
b100001 &
#345
b10 %
b10 (
b100010 &
#355
1!
0"
b11 %
b11 (
b100011 &
#365
b100 %
b100 (
b100100 &
#375
1!
b101 %
b101 (
b100101 &
#385
b110 %
b110 (
b100110 &
#395
1!
b111 %
b111 (
b100111 &
#405
b1000 %
b1000 (
b101000 &
#415
1!
b1001 %
b1001 (
b101001 &
#425
b1010 %
b1010 (
b101010 &
#435
1!
b1011 %
b1011 (
b101011 &
#445
b1100 %
b1100 (
b101100 &
#455
1!
b1101 %
b1101 (
b101101 &
#465
b1110 %
b1110 (
b101110 &
#475
1!
b1111 %
b1111 (
b101111 &
#485
b11 $
b11 '
b0 %
b0 (
b110000 &
#495
1"
0!
b1 %
b1 (
b110001 &
#505
b10 %
b10 (
b110010 &
#515
1#
0"
b11 %
b11 (
b110011 &
#525
b100 %
b100 (
b110100 &
#535
1!
0#
b101 %
b101 (
b110101 &
#545
b110 %
b110 (
b110110 &
#555
1!
b111 %
b111 (
b110111 &
#565
b1000 %
b1000 (
b111000 &
#575
1!
b1001 %
b1001 (
b111001 &
#585
b1010 %
b1010 (
b111010 &
#595
1!
b1011 %
b1011 (
b111011 &
#605
b1100 %
b1100 (
b111100 &
#615
1!
b1101 %
b1101 (
b111101 &
#625
b1110 %
b1110 (
b111110 &
#635
1!
b1111 %
b1111 (
b111111 &
#645
b100 $
b100 '
b0 %
b0 (
b1000000 &
#655
1"
0!
b1 %
b1 (
b1000001 &
#665
b10 %
b10 (
b1000010 &
#675
1"
b11 %
b11 (
b1000011 &
#685
b100 %
b100 (
b1000100 &
#695
1!
0"
b101 %
b101 (
b1000101 &
#705
b110 %
b110 (
b1000110 &
#715
1!
b111 %
b111 (
b1000111 &
#725
b1000 %
b1000 (
b1001000 &
#735
1!
b1001 %
b1001 (
b1001001 &
#745
b1010 %
b1010 (
b1001010 &
#755
1!
b1011 %
b1011 (
b1001011 &
#765
b1100 %
b1100 (
b1001100 &
#775
1!
b1101 %
b1101 (
b1001101 &
#785
b1110 %
b1110 (
b1001110 &
#795
1!
b1111 %
b1111 (
b1001111 &
#805
b101 $
b101 '
b0 %
b0 (
b1010000 &
#815
1"
0!
b1 %
b1 (
b1010001 &
#825
b10 %
b10 (
b1010010 &
#835
1"
b11 %
b11 (
b1010011 &
#845
b100 %
b100 (
b1010100 &
#855
1#
0"
b101 %
b101 (
b1010101 &
#865
b110 %
b110 (
b1010110 &
#875
1!
0#
b111 %
b111 (
b1010111 &
#885
b1000 %
b1000 (
b1011000 &
#895
1!
b1001 %
b1001 (
b1011001 &
#905
b1010 %
b1010 (
b1011010 &
#915
1!
b1011 %
b1011 (
b1011011 &
#925
b1100 %
b1100 (
b1011100 &
#935
1!
b1101 %
b1101 (
b1011101 &
#945
b1110 %
b1110 (
b1011110 &
#955
1!
b1111 %
b1111 (
b1011111 &
#965
b110 $
b110 '
b0 %
b0 (
b1100000 &
#975
1"
0!
b1 %
b1 (
b1100001 &
#985
b10 %
b10 (
b1100010 &
#995
1"
b11 %
b11 (
b1100011 &
#1005
b100 %
b100 (
b1100100 &
#1015
1"
b101 %
b101 (
b1100101 &
#1025
b110 %
b110 (
b1100110 &
#1035
1!
0"
b111 %
b111 (
b1100111 &
#1045
b1000 %
b1000 (
b1101000 &
#1055
1!
b1001 %
b1001 (
b1101001 &
#1065
b1010 %
b1010 (
b1101010 &
#1075
1!
b1011 %
b1011 (
b1101011 &
#1085
b1100 %
b1100 (
b1101100 &
#1095
1!
b1101 %
b1101 (
b1101101 &
#1105
b1110 %
b1110 (
b1101110 &
#1115
1!
b1111 %
b1111 (
b1101111 &
#1125
b111 $
b111 '
b0 %
b0 (
b1110000 &
#1135
1"
0!
b1 %
b1 (
b1110001 &
#1145
b10 %
b10 (
b1110010 &
#1155
1"
b11 %
b11 (
b1110011 &
#1165
b100 %
b100 (
b1110100 &
#1175
1"
b101 %
b101 (
b1110101 &
#1185
b110 %
b110 (
b1110110 &
#1195
1#
0"
b111 %
b111 (
b1110111 &
#1205
b1000 %
b1000 (
b1111000 &
#1215
1!
0#
b1001 %
b1001 (
b1111001 &
#1225
b1010 %
b1010 (
b1111010 &
#1235
1!
b1011 %
b1011 (
b1111011 &
#1245
b1100 %
b1100 (
b1111100 &
#1255
1!
b1101 %
b1101 (
b1111101 &
#1265
b1110 %
b1110 (
b1111110 &
#1275
1!
b1111 %
b1111 (
b1111111 &
#1285
b1000 $
b1000 '
b0 %
b0 (
b10000000 &
#1295
1"
0!
b1 %
b1 (
b10000001 &
#1305
b10 %
b10 (
b10000010 &
#1315
1"
b11 %
b11 (
b10000011 &
#1325
b100 %
b100 (
b10000100 &
#1335
1"
b101 %
b101 (
b10000101 &
#1345
b110 %
b110 (
b10000110 &
#1355
1"
b111 %
b111 (
b10000111 &
#1365
b1000 %
b1000 (
b10001000 &
#1375
1!
0"
b1001 %
b1001 (
b10001001 &
#1385
b1010 %
b1010 (
b10001010 &
#1395
1!
b1011 %
b1011 (
b10001011 &
#1405
b1100 %
b1100 (
b10001100 &
#1415
1!
b1101 %
b1101 (
b10001101 &
#1425
b1110 %
b1110 (
b10001110 &
#1435
1!
b1111 %
b1111 (
b10001111 &
#1445
b1001 $
b1001 '
b0 %
b0 (
b10010000 &
#1455
1"
0!
b1 %
b1 (
b10010001 &
#1465
b10 %
b10 (
b10010010 &
#1475
1"
b11 %
b11 (
b10010011 &
#1485
b100 %
b100 (
b10010100 &
#1495
1"
b101 %
b101 (
b10010101 &
#1505
b110 %
b110 (
b10010110 &
#1515
1"
b111 %
b111 (
b10010111 &
#1525
b1000 %
b1000 (
b10011000 &
#1535
1#
0"
b1001 %
b1001 (
b10011001 &
#1545
b1010 %
b1010 (
b10011010 &
#1555
1!
0#
b1011 %
b1011 (
b10011011 &
#1565
b1100 %
b1100 (
b10011100 &
#1575
1!
b1101 %
b1101 (
b10011101 &
#1585
b1110 %
b1110 (
b10011110 &
#1595
1!
b1111 %
b1111 (
b10011111 &
#1605
b1010 $
b1010 '
b0 %
b0 (
b10100000 &
#1615
1"
0!
b1 %
b1 (
b10100001 &
#1625
b10 %
b10 (
b10100010 &
#1635
1"
b11 %
b11 (
b10100011 &
#1645
b100 %
b100 (
b10100100 &
#1655
1"
b101 %
b101 (
b10100101 &
#1665
b110 %
b110 (
b10100110 &
#1675
1"
b111 %
b111 (
b10100111 &
#1685
b1000 %
b1000 (
b10101000 &
#1695
1"
b1001 %
b1001 (
b10101001 &
#1705
b1010 %
b1010 (
b10101010 &
#1715
1!
0"
b1011 %
b1011 (
b10101011 &
#1725
b1100 %
b1100 (
b10101100 &
#1735
1!
b1101 %
b1101 (
b10101101 &
#1745
b1110 %
b1110 (
b10101110 &
#1755
1!
b1111 %
b1111 (
b10101111 &
#1765
b1011 $
b1011 '
b0 %
b0 (
b10110000 &
#1775
1"
0!
b1 %
b1 (
b10110001 &
#1785
b10 %
b10 (
b10110010 &
#1795
1"
b11 %
b11 (
b10110011 &
#1805
b100 %
b100 (
b10110100 &
#1815
1"
b101 %
b101 (
b10110101 &
#1825
b110 %
b110 (
b10110110 &
#1835
1"
b111 %
b111 (
b10110111 &
#1845
b1000 %
b1000 (
b10111000 &
#1855
1"
b1001 %
b1001 (
b10111001 &
#1865
b1010 %
b1010 (
b10111010 &
#1875
1#
0"
b1011 %
b1011 (
b10111011 &
#1885
b1100 %
b1100 (
b10111100 &
#1895
1!
0#
b1101 %
b1101 (
b10111101 &
#1905
b1110 %
b1110 (
b10111110 &
#1915
1!
b1111 %
b1111 (
b10111111 &
#1925
b1100 $
b1100 '
b0 %
b0 (
b11000000 &
#1935
1"
0!
b1 %
b1 (
b11000001 &
#1945
b10 %
b10 (
b11000010 &
#1955
1"
b11 %
b11 (
b11000011 &
#1965
b100 %
b100 (
b11000100 &
#1975
1"
b101 %
b101 (
b11000101 &
#1985
b110 %
b110 (
b11000110 &
#1995
1"
b111 %
b111 (
b11000111 &
#2005
b1000 %
b1000 (
b11001000 &
#2015
1"
b1001 %
b1001 (
b11001001 &
#2025
b1010 %
b1010 (
b11001010 &
#2035
1"
b1011 %
b1011 (
b11001011 &
#2045
b1100 %
b1100 (
b11001100 &
#2055
1!
0"
b1101 %
b1101 (
b11001101 &
#2065
b1110 %
b1110 (
b11001110 &
#2075
1!
b1111 %
b1111 (
b11001111 &
#2085
b1101 $
b1101 '
b0 %
b0 (
b11010000 &
#2095
1"
0!
b1 %
b1 (
b11010001 &
#2105
b10 %
b10 (
b11010010 &
#2115
1"
b11 %
b11 (
b11010011 &
#2125
b100 %
b100 (
b11010100 &
#2135
1"
b101 %
b101 (
b11010101 &
#2145
b110 %
b110 (
b11010110 &
#2155
1"
b111 %
b111 (
b11010111 &
#2165
b1000 %
b1000 (
b11011000 &
#2175
1"
b1001 %
b1001 (
b11011001 &
#2185
b1010 %
b1010 (
b11011010 &
#2195
1"
b1011 %
b1011 (
b11011011 &
#2205
b1100 %
b1100 (
b11011100 &
#2215
1#
0"
b1101 %
b1101 (
b11011101 &
#2225
b1110 %
b1110 (
b11011110 &
#2235
1!
0#
b1111 %
b1111 (
b11011111 &
#2245
b1110 $
b1110 '
b0 %
b0 (
b11100000 &
#2255
1"
0!
b1 %
b1 (
b11100001 &
#2265
b10 %
b10 (
b11100010 &
#2275
1"
b11 %
b11 (
b11100011 &
#2285
b100 %
b100 (
b11100100 &
#2295
1"
b101 %
b101 (
b11100101 &
#2305
b110 %
b110 (
b11100110 &
#2315
1"
b111 %
b111 (
b11100111 &
#2325
b1000 %
b1000 (
b11101000 &
#2335
1"
b1001 %
b1001 (
b11101001 &
#2345
b1010 %
b1010 (
b11101010 &
#2355
1"
b1011 %
b1011 (
b11101011 &
#2365
b1100 %
b1100 (
b11101100 &
#2375
1"
b1101 %
b1101 (
b11101101 &
#2385
b1110 %
b1110 (
b11101110 &
#2395
1!
0"
b1111 %
b1111 (
b11101111 &
#2405
b1111 $
b1111 '
b0 %
b0 (
b11110000 &
#2415
1"
0!
b1 %
b1 (
b11110001 &
#2425
b10 %
b10 (
b11110010 &
#2435
1"
b11 %
b11 (
b11110011 &
#2445
b100 %
b100 (
b11110100 &
#2455
1"
b101 %
b101 (
b11110101 &
#2465
b110 %
b110 (
b11110110 &
#2475
1"
b111 %
b111 (
b11110111 &
#2485
b1000 %
b1000 (
b11111000 &
#2495
1"
b1001 %
b1001 (
b11111001 &
#2505
b1010 %
b1010 (
b11111010 &
#2515
1"
b1011 %
b1011 (
b11111011 &
#2525
b1100 %
b1100 (
b11111100 &
#2535
1"
b1101 %
b1101 (
b11111101 &
#2545
b1110 %
b1110 (
b11111110 &
#2555
1#
0"
b1111 %
b1111 (
b11111111 &
#2565
b100000000 &
