08_Finite_State_Machines/070_Sequence_Detector_101/behavioural.v
module sequence_detector_101 (

input clk,
input rst,
input x,

output reg y

);

parameter S0 = 2'b00,
          S1 = 2'b01,
          S2 = 2'b10,
          S3 = 2'b11;

reg [1:0] present_state, next_state;

always @(posedge clk or posedge rst) begin

if (rst)

present_state <= S0;

else 

present_state <= next_state;

end

always @(*) begin

case(present_state)

S0: begin

if(x)
next_state <= S1;
else
next_state <= S0;

end

S1: begin

if (x)
next_state <= S1;
else
next_state <= S2;

end

S2: begin

if(x)
next_state <= S3;
else
next_state <= S0;
end

S3: begin

if(x)
next_state <= S1;
else
next_state <= S2;

end

default: next_state <= S0;

endcase

end

always @(*) begin
	case(present_state)
		S3: y = 1;
		default: y = 0;

	endcase

end

endmodule

08_Finite_State_Machines/070_Sequence_Detector_101/tb_sequence_detector_101.v
module tb_sequence_detector_101;

reg clk;
reg rst;
reg x;

wire y;

integer i;
reg [9:0] input_seq;

sequence_detector_101 DUT (.clk(clk), .rst(rst), .x(x), .y(y));

initial begin
    clk = 0;
    forever #5 clk = ~clk;
end

always @(posedge clk or negedge clk) begin

if(clk)
$display("Time = %0t:Rising Edge", $time);
else
$display("Time = %0t:Falling Edge", $time);

end

initial begin

    $dumpfile("sequence_detector_101.vcd");
    $dumpvars(0, tb_sequence_detector_101);

    $monitor("Time=%0t | clk = %b| rst=%b | x=%b | state = %b | y=%b",
              $time, clk, rst, x, DUT.present_state, y);

    input_seq = 10'b1010100101;

    rst = 1;
    x = 0;

   #10 rst = 0;
   
   for (i = 0; i < 10; i = i +1) begin
    
     #10;	  
     x = input_seq[i];
   
   end
    
#200;

$finish;

end

endmodule

08_Finite_State_Machines/070_Sequence_Detector_101/sequence_detector_101.vcd
$date
	Sat Jul  4 14:01:49 2026
$end
$version
	Icarus Verilog
$end
$timescale
	1s
$end
$scope module tb_sequence_detector_101 $end
$var wire 1 ! y $end
$var reg 1 " clk $end
$var reg 10 # input_seq [9:0] $end
$var reg 1 $ rst $end
$var reg 1 % x $end
$var integer 32 & i [31:0] $end
$scope module DUT $end
$var wire 1 " clk $end
$var wire 1 $ rst $end
$var wire 1 % x $end
$var parameter 2 ' S0 $end
$var parameter 2 ( S1 $end
$var parameter 2 ) S2 $end
$var parameter 2 * S3 $end
$var reg 2 + next_state [1:0] $end
$var reg 2 , present_state [1:0] $end
$var reg 1 ! y $end
$upscope $end
$upscope $end
$enddefinitions $end
$comment Show the parameter values. $end
$dumpall
b11 *
b10 )
b1 (
b0 '
$end
#0
$dumpvars
b0 ,
b0 +
bx &
0%
1$
b1010100101 #
0"
0!
$end
#5
1"
#10
0"
b0 &
0$
#15
1"
#20
b1 +
0"
b1 &
1%
#25
b1 ,
1"
#30
b10 +
0"
b10 &
0%
#35
b0 +
b10 ,
1"
#40
b11 +
0"
b11 &
1%
#45
b1 +
1!
b11 ,
1"
#50
b10 +
0"
b100 &
0%
#55
b0 +
0!
b10 ,
1"
#60
0"
b101 &
#65
b0 ,
1"
#70
b1 +
0"
b110 &
1%
#75
b1 ,
1"
#80
b10 +
0"
b111 &
0%
#85
b0 +
b10 ,
1"
#90
b11 +
0"
b1000 &
1%
#95
b1 +
1!
b11 ,
1"
#100
b10 +
0"
b1001 &
0%
#105
b0 +
0!
b10 ,
1"
#110
b11 +
0"
b1010 &
1%
#115
b1 +
1!
b11 ,
1"
#120
0"
#125
0!
b1 ,
1"
