02_Basic_Combinational/009_Full_Adder/behavioural.v
module full_adder(

input a, b, cin,
output reg sum, carry

);

integer i;

always@ (*) begin 

for(i = 0; i < 1; i = i + 1)

begin

sum = a ^ b ^ cin;
carry = (a & b) | ( b & cin ) | ( cin & a);

end 

end 

endmodule

02_Basic_Combinational/009_Full_Adder/tb_full_adder.v
module tb_full_adder;

reg a, b, cin;
wire sum, carry;
integer i;

full_adder DUT (.a(a), .b(b), .cin(cin), .sum(sum), .carry(carry));

initial begin

$dumpfile ("full_adder.vcd");
$dumpvars (0, tb_full_adder);

$display("----------------------------------");
$display("-----------Full Adder-------------");
$display("----------------------------------");

$monitor ("Time = %t | a = %b | b = %b | cin = %b | sum = %b | carry = %b", $time, a, b, cin , sum , carry);

for (i = 0; i < 8 ; i = i +1)

begin

{a, b, cin} = i;
#10;

end

end 

endmodule

02_Basic_Combinational/009_Full_Adder/full_adder.vcd
$date
	Thu Jun 25 08:59:42 2026
$end
$version
	Icarus Verilog
$end
$timescale
	1s
$end
$scope module tb_full_adder $end
$var wire 1 ! sum $end
$var wire 1 " carry $end
$var reg 1 # a $end
$var reg 1 $ b $end
$var reg 1 % cin $end
$var integer 32 & i [31:0] $end
$scope module DUT $end
$var wire 1 # a $end
$var wire 1 $ b $end
$var wire 1 % cin $end
$var reg 1 " carry $end
$var reg 1 ! sum $end
$var integer 32 ' i [31:0] $end
$upscope $end
$upscope $end
$enddefinitions $end
$comment Show the parameter values. $end
$dumpall
$end
#0
$dumpvars
b1 '
b0 &
0%
0$
0#
0"
0!
$end
#10
1!
b1 '
1%
b1 &
#20
b1 '
1$
0%
b10 &
#30
1"
0!
b1 '
1%
b11 &
#40
0"
1!
b1 '
1#
0$
0%
b100 &
#50
1"
0!
b1 '
1%
b101 &
#60
b1 '
1$
0%
b110 &
#70
1!
b1 '
1%
b111 &
#80
b1000 &
