08_Finite_State_Machines/072_Even_Odd_Zero_Detector/behavioural.v
module even_odd_zero_detector (

input clk,
input rst,
input x,

output reg y

);

parameter ODD  = 1'b0,
          EVEN = 1'b1;

reg present_state, next_state;

always @(posedge clk or posedge rst) begin

if(rst)
present_state <= ODD;
else
present_state <= next_state;

end

always @(*) begin

case (present_state)

ODD: begin

if (x == 0)

next_state = EVEN;

else

next_state = ODD;

end

EVEN: begin

if (x == 0)

next_state = ODD;

else

next_state = EVEN;

end

default: next_state = ODD;

endcase

end

always @(*)

case(present_state)

ODD: y = 0;
EVEN: y = 1;

default: y = 0;

endcase

endmodule

08_Finite_State_Machines/072_Even_Odd_Zero_Detector/tb_odd_even.v
module tb_even_odd_zero_detector;

reg clk;
reg rst;
reg x;

wire y;

integer i;

reg [9:0] input_seq;

even_odd_zero_detector UUT (.clk(clk), .rst(rst), .x(x), .y(y));

initial clk = 0;
always #5 clk = ~clk;

always @(posedge clk or negedge clk)
begin
    if(clk)
        $display("\nTime=%0t : Rising Edge",$time);
    else
        $display("Time=%0t : Falling Edge",$time);
end

initial
begin

    $dumpfile("even_odd_zero_detector.vcd");
    $dumpvars(0,tb_even_odd_zero_detector);

    $monitor("Time=%0t | clk=%b | rst=%b | x=%b | state=%b | y=%b",
              $time,clk,rst,x,UUT.present_state,y);

      input_seq = 10'b1001000101;
      
      rst = 1;
      x = 0;

      #10;

      rst = 0;

      for (i = 0; i < 10; i = i +1)
      begin
          @(negedge clk);
          x = input_seq [i];
         

  end

#20;
$finish;

end

endmodule

08_Finite_State_Machines/072_Even_Odd_Zero_Detector/even_odd_zero_detector.vcd
$date
	Mon Jul  6 05:06:33 2026
$end
$version
	Icarus Verilog
$end
$timescale
	1s
$end
$scope module tb_even_odd_zero_detector $end
$var wire 1 ! y $end
$var reg 1 " clk $end
$var reg 10 # input_seq [9:0] $end
$var reg 1 $ rst $end
$var reg 1 % x $end
$var integer 32 & i [31:0] $end
$scope module UUT $end
$var wire 1 " clk $end
$var wire 1 $ rst $end
$var wire 1 % x $end
$var parameter 1 ' EVEN $end
$var parameter 1 ( ODD $end
$var reg 1 ) next_state $end
$var reg 1 * present_state $end
$var reg 1 ! y $end
$upscope $end
$upscope $end
$enddefinitions $end
$comment Show the parameter values. $end
$dumpall
0(
1'
$end
#0
$dumpvars
0*
1)
bx &
0%
1$
b1001000101 #
0"
0!
$end
#5
1"
#10
0)
1%
0"
b1 &
0$
#15
1"
#20
1)
b10 &
0%
0"
#25
1!
0)
1*
1"
#30
1)
b11 &
1%
0"
#35
1"
#40
0)
b100 &
0%
0"
#45
0!
1)
0*
1"
#50
b101 &
0"
#55
1!
0)
1*
1"
#60
b110 &
0"
#65
0!
1)
0*
1"
#70
0)
b111 &
1%
0"
#75
1"
#80
1)
b1000 &
0%
0"
#85
1!
0)
1*
1"
#90
b1001 &
0"
#95
0!
1)
0*
1"
#100
0)
b1010 &
1%
0"
