03_Intermediate_Combinational/027_Parity_Generator/behavioural.v
module parity_generator (

input [3:0] a,
output reg odd_parity,
output reg even_parity

);

always@ (*) begin

if (^a) begin

odd_parity = 0;
even_parity = 1;

end

else begin

even_parity = 0;
odd_parity = 1;

end

end

endmodule

03_Intermediate_Combinational/027_Parity_Generator/tb_parity_generator.v
module tb_parity_generator;

reg [3:0] a;

wire even_parity;
wire odd_parity;

integer i;

parity_generator DUT (.a(a), .even_parity(even_parity), .odd_parity(odd_parity));

initial begin

$dumpfile ("parity_generator.vcd");
$dumpvars (0, tb_parity_generator);

$monitor (" Time = %0t | a = %b | even_parity = %b | odd_parity = %b", $time, a, even_parity, odd_parity);

for (i = 0; i < 16; i = i+1) begin

a = i;

#10;

end

$finish;

end

endmodule

03_Intermediate_Combinational/027_Parity_Generator/parity_generator.vcd
$date
	Tue Jun 30 15:58:10 2026
$end
$version
	Icarus Verilog
$end
$timescale
	1s
$end
$scope module tb_parity_generator $end
$var wire 1 ! odd_parity $end
$var wire 1 " even_parity $end
$var reg 4 # a [3:0] $end
$var integer 32 $ i [31:0] $end
$scope module DUT $end
$var wire 4 % a [3:0] $end
$var reg 1 " even_parity $end
$var reg 1 ! odd_parity $end
$upscope $end
$upscope $end
$enddefinitions $end
$comment Show the parameter values. $end
$dumpall
$end
#0
$dumpvars
b0 %
b0 $
b0 #
0"
1!
$end
#10
1"
0!
b1 #
b1 %
b1 $
#20
b10 #
b10 %
b10 $
#30
1!
0"
b11 #
b11 %
b11 $
#40
1"
0!
b100 #
b100 %
b100 $
#50
1!
0"
b101 #
b101 %
b101 $
#60
b110 #
b110 %
b110 $
#70
1"
0!
b111 #
b111 %
b111 $
#80
b1000 #
b1000 %
b1000 $
#90
1!
0"
b1001 #
b1001 %
b1001 $
#100
b1010 #
b1010 %
b1010 $
#110
1"
0!
b1011 #
b1011 %
b1011 $
#120
1!
0"
b1100 #
b1100 %
b1100 $
#130
1"
0!
b1101 #
b1101 %
b1101 $
#140
b1110 #
b1110 %
b1110 $
#150
1!
0"
b1111 #
b1111 %
b1111 $
#160
b10000 $
