06_Registers/057_Universal_Shift_Register/behavioural.v
module universal_shift_register(

input clk,
input rst,
input [2:1] s,
input shift_left_in,
input shift_right_in,
input [3:0] parallel_in,

output reg [3:0] q

);

parameter HOLD = 2'b00,
          SHIFT_RIGHT = 2'b01,
          SHIFT_LEFT = 2'b10,
          PARALLEL_LOAD = 2'b11;


always @(posedge clk or posedge rst) begin

if (rst)

q <= 4'b0000;

else begin

case({s[2], s[1]})

HOLD: q <= q;

SHIFT_RIGHT: q <= {shift_right_in, q[3:1]};

SHIFT_LEFT: q <= {q[2:0], shift_left_in};

PARALLEL_LOAD: q <= parallel_in;

endcase

end

end

endmodule

06_Registers/057_Universal_Shift_Register/tb_universal_register.v
module tb_universal_register;

reg clk;
reg rst;
reg [2:1] s;
reg shift_left_in;
reg shift_right_in;
reg [3:0] parallel_in;

wire [3:0] q;

integer i;

universal_shift_register UUT (.clk(clk), .rst(rst), .s(s), .shift_right_in(shift_right_in), .shift_left_in(shift_left_in), .parallel_in(parallel_in), .q(q));

reg [3:0] right_data;
reg [3:0] left_data;

initial clk = 0;
always #5 clk = ~clk;

always @(posedge clk or negedge clk) begin
	if (clk)
		$display("\nTime = %0t: Rising Edge", $time);
	else
		$display("Time = %0t: Falling Edge", $time);

end

initial begin

	$dumpfile ("universal_register.vcd");
	$dumpvars (0, tb_universal_register);

	$monitor("Time = %0t | clk = %b | rst = %b | s[2] = %b | s[1] = %b | shift_right_in = %b | shift_left_in = %b | parallel_in = %b | q = %b|", $time, clk, rst, s[2], s[1], shift_right_in, shift_left_in, parallel_in, q);

 rst = 1;
 s[2:1] = 0;
 shift_right_in = 0;
 shift_left_in = 0;
 parallel_in = 4'b0000;

 #10 rst = 0;

 $display ("\n============HOLD==============");

 s[2:1] = {1'b0, 1'b0};

 #20;

 $display ("\n============SHIFT_RIGHT_IN===========");

 s[2:1] = {1'b0, 1'b1};
 right_data = 4'b1011;

 for (i = 0; i < 4; i = i +1) begin

          shift_right_in = right_data[i];
          #10;
   end

   $display ("\n=============SHIFT_LEFT_IN==============");

   s[2:1] = {1'b1, 1'b0};
   left_data = 4'b1011;

   for (i = 0; i < 4; i = i + 1) begin

	   shift_left_in = left_data[i];
	   #10;

     end

     $display("\n=================PARALLEL_LOAD==========");
    
       s[2:1] = {1'b1, 1'b1};

       parallel_in = 4'b1011;
       #10;



       
$finish;

end


endmodule

06_Registers/057_Universal_Shift_Register/universal_register.vcd
$date
	Fri Jul  3 08:40:16 2026
$end
$version
	Icarus Verilog
$end
$timescale
	1s
$end
$scope module tb_universal_register $end
$var wire 4 ! q [3:0] $end
$var reg 1 " clk $end
$var reg 4 # left_data [3:0] $end
$var reg 4 $ parallel_in [3:0] $end
$var reg 4 % right_data [3:0] $end
$var reg 1 & rst $end
$var reg 2 ' s [2:1] $end
$var reg 1 ( shift_left_in $end
$var reg 1 ) shift_right_in $end
$var integer 32 * i [31:0] $end
$scope module UUT $end
$var wire 1 " clk $end
$var wire 4 + parallel_in [3:0] $end
$var wire 1 & rst $end
$var wire 2 , s [2:1] $end
$var wire 1 ( shift_left_in $end
$var wire 1 ) shift_right_in $end
$var parameter 2 - HOLD $end
$var parameter 2 . PARALLEL_LOAD $end
$var parameter 2 / SHIFT_LEFT $end
$var parameter 2 0 SHIFT_RIGHT $end
$var reg 4 1 q [3:0] $end
$upscope $end
$upscope $end
$enddefinitions $end
$comment Show the parameter values. $end
$dumpall
b1 0
b10 /
b11 .
b0 -
$end
#0
$dumpvars
b0 1
b0 ,
b0 +
bx *
0)
0(
b0 '
1&
bx %
b0 $
bx #
0"
b0 !
$end
#5
1"
#10
0"
0&
#15
1"
#20
0"
#25
1"
#30
0"
1)
b0 *
b1011 %
b1 '
b1 ,
#35
b1000 !
b1000 1
1"
#40
0"
b1 *
#45
b1100 !
b1100 1
1"
#50
0"
0)
b10 *
#55
b110 !
b110 1
1"
#60
0"
1)
b11 *
#65
b1011 !
b1011 1
1"
#70
0"
1(
b1011 #
b10 '
b10 ,
b0 *
#75
b111 !
b111 1
1"
#80
0"
b1 *
#85
b1111 !
b1111 1
1"
#90
0"
0(
b10 *
#95
b1110 !
b1110 1
1"
#100
0"
1(
b11 *
#105
b1101 !
b1101 1
1"
#110
0"
b1011 $
b1011 +
b11 '
b11 ,
b100 *
#115
b1011 !
b1011 1
1"
