02_Basic_Combinational/018_Encoder/gatelevel.v
module encoder (

input a,
input b,
input c,
input d,

output x,
output y

);


or (x, c, d);
or (y, b, d);

endmodule

02_Basic_Combinational/018_Encoder/tb_encoder.v
module tb_encoder;

reg a; 
reg b; 
reg c;
reg d;

wire x;
wire y;

integer i;

encoder DUT (.a(a), .b(b), .c(c), .d(d), .x(x), .y(y));

initial begin 

$dumpfile ("encoder.vcd");
$dumpvars (0, tb_encoder);

$monitor ("Time = 0%t | a = %b | b = %b | c = %b | d = %b | x = %b | y = %b ", $time, a, b, c, d, x, y);

for (i = 0; i < 16; i = i+1)

begin

{a, b, c, d} = i;

#10;

end

$finish;

end

endmodule

02_Basic_Combinational/018_Encoder/encoder.vcd
$date
	Sat Jun 27 10:38:33 2026
$end
$version
	Icarus Verilog
$end
$timescale
	1s
$end
$scope module tb_encoder $end
$var wire 1 ! y $end
$var wire 1 " x $end
$var reg 1 # a $end
$var reg 1 $ b $end
$var reg 1 % c $end
$var reg 1 & d $end
$var integer 32 ' i [31:0] $end
$scope module DUT $end
$var wire 1 # a $end
$var wire 1 $ b $end
$var wire 1 % c $end
$var wire 1 & d $end
$var wire 1 " x $end
$var wire 1 ! y $end
$upscope $end
$upscope $end
$enddefinitions $end
$comment Show the parameter values. $end
$dumpall
$end
#0
$dumpvars
b0 '
0&
0%
0$
0#
0"
0!
$end
#10
1"
1!
1&
b1 '
#20
0!
1%
0&
b10 '
#30
1!
1&
b11 '
#40
0"
1$
0%
0&
b100 '
#50
1"
1&
b101 '
#60
1%
0&
b110 '
#70
1&
b111 '
#80
0"
0!
1#
0$
0%
0&
b1000 '
#90
1"
1!
1&
b1001 '
#100
0!
1%
0&
b1010 '
#110
1!
1&
b1011 '
#120
0"
1$
0%
0&
b1100 '
#130
1"
1&
b1101 '
#140
1%
0&
b1110 '
#150
1&
b1111 '
#160
b10000 '
