03_Intermediate_Combinational/025_Binary_to_Gray/dataflow.v
module binary_to_gray (

input [3:0] bin,
output [3:0] gray

);

assign gray [3] = bin [3];
assign gray [2] = bin [3] ^ bin[2];
assign gray [1] = bin [2] ^ bin[1];
assign gray [0] = bin [1] ^ bin[0];

endmodule

03_Intermediate_Combinational/025_Binary_to_Gray/tb_binary_to_gray.v
module tb_binary_to_gray;

reg [3:0] bin;
wire [3:0] gray;

integer i;

binary_to_gray DUT (.bin(bin), .gray(gray));

initial begin

	$dumpfile ("binary_to_gray.vcd");
	$dumpvars (0, tb_binary_to_gray);

	$monitor (" Time = %0t | bin = %b | gray = %b", $time, bin, gray);

	for (i = 0; i < 16; i = i + 1) begin
		bin = i;

		#10;

	end

	$finish;
	
end


endmodule

03_Intermediate_Combinational/025_Binary_to_Gray/binary_to_gray.vcd
$date
	Tue Jun 30 14:41:43 2026
$end
$version
	Icarus Verilog
$end
$timescale
	1s
$end
$scope module tb_binary_to_gray $end
$var wire 4 ! gray [3:0] $end
$var reg 4 " bin [3:0] $end
$var integer 32 # i [31:0] $end
$scope module DUT $end
$var wire 4 $ bin [3:0] $end
$var reg 4 % gray [3:0] $end
$upscope $end
$upscope $end
$enddefinitions $end
$comment Show the parameter values. $end
$dumpall
$end
#0
$dumpvars
b0 %
b0 $
b0 #
b0 "
b0 !
$end
#10
b1 !
b1 %
b1 "
b1 $
b1 #
#20
b11 !
b11 %
b10 "
b10 $
b10 #
#30
b10 !
b10 %
b11 "
b11 $
b11 #
#40
b110 !
b110 %
b100 "
b100 $
b100 #
#50
b111 !
b111 %
b101 "
b101 $
b101 #
#60
b101 !
b101 %
b110 "
b110 $
b110 #
#70
b100 !
b100 %
b111 "
b111 $
b111 #
#80
b1100 !
b1100 %
b1000 "
b1000 $
b1000 #
#90
b1101 !
b1101 %
b1001 "
b1001 $
b1001 #
#100
b1111 !
b1111 %
b1010 "
b1010 $
b1010 #
#110
b1110 !
b1110 %
b1011 "
b1011 $
b1011 #
#120
b1010 !
b1010 %
b1100 "
b1100 $
b1100 #
#130
b1011 !
b1011 %
b1101 "
b1101 $
b1101 #
#140
b1001 !
b1001 %
b1110 "
b1110 $
b1110 #
#150
b1000 !
b1000 %
b1111 "
b1111 $
b1111 #
#160
b10000 #
