06_Registers/050_4bit_Register/behavioural.v
module register_4bit (

input [3:0] d,
input clk,
input rst,
output reg [3:0] q

);

always @(posedge clk or posedge rst) begin

if (rst) 

q <= 4'b0000;

else 

q <= d;

end

endmodule

06_Registers/050_4bit_Register/tb_4bit_Register.v
module tb_register_4bit;

reg [3:0] d;
reg clk;
reg rst;

wire [3:0] q;

integer i;

register_4bit UUT(.d(d), .clk(clk), .rst(rst), .q(q));


initial clk = 0;
always #5 clk = ~clk;

always @(posedge clk or negedge clk) begin

if(clk)
$display ("Time = %0t: Rising Time", $time);
else
$display ("Time = %0t: Falling Time", $time);

end

initial begin

$dumpfile ("register_4bit.vcd");
$dumpvars (0, tb_register_4bit);

#5;
$monitor("Time = %0t | clk = %b | rst = %b | d = %b | q = %b", $time, clk, rst, d, q);

rst = 1;
d = 0;

rst =0;

for (i = 0; i < 16; i = i +1) begin

d = i;
#10;

end

$finish;

end

endmodule

06_Registers/050_4bit_Register/register_4bit.vcd
$date
	Thu Jul  2 10:24:51 2026
$end
$version
	Icarus Verilog
$end
$timescale
	1s
$end
$scope module tb_register_4bit $end
$var wire 4 ! q [3:0] $end
$var reg 1 " clk $end
$var reg 4 # d [3:0] $end
$var reg 1 $ rst $end
$var integer 32 % i [31:0] $end
$scope module UUT $end
$var wire 1 " clk $end
$var wire 4 & d [3:0] $end
$var wire 1 $ rst $end
$var reg 4 ' q [3:0] $end
$upscope $end
$upscope $end
$enddefinitions $end
$comment Show the parameter values. $end
$dumpall
$end
#0
$dumpvars
bx '
bx &
bx %
x$
bx #
0"
bx !
$end
#5
b0 !
b0 '
b0 %
b0 #
b0 &
0$
1"
#10
0"
#15
b1 !
b1 '
1"
b1 #
b1 &
b1 %
#20
0"
#25
b10 !
b10 '
1"
b10 #
b10 &
b10 %
#30
0"
#35
b11 !
b11 '
1"
b11 #
b11 &
b11 %
#40
0"
#45
b100 !
b100 '
1"
b100 #
b100 &
b100 %
#50
0"
#55
b101 !
b101 '
1"
b101 #
b101 &
b101 %
#60
0"
#65
b110 !
b110 '
1"
b110 #
b110 &
b110 %
#70
0"
#75
b111 !
b111 '
1"
b111 #
b111 &
b111 %
#80
0"
#85
b1000 !
b1000 '
1"
b1000 #
b1000 &
b1000 %
#90
0"
#95
b1001 !
b1001 '
1"
b1001 #
b1001 &
b1001 %
#100
0"
#105
b1010 !
b1010 '
1"
b1010 #
b1010 &
b1010 %
#110
0"
#115
b1011 !
b1011 '
1"
b1011 #
b1011 &
b1011 %
#120
0"
#125
b1100 !
b1100 '
1"
b1100 #
b1100 &
b1100 %
#130
0"
#135
b1101 !
b1101 '
1"
b1101 #
b1101 &
b1101 %
#140
0"
#145
b1110 !
b1110 '
1"
b1110 #
b1110 &
b1110 %
#150
0"
#155
b1111 !
b1111 '
1"
b1111 #
b1111 &
b1111 %
#160
0"
#165
1"
b10000 %
