07_Counters/062_Mod_10_Counter/behavioural.v
module mod10_counter(

input clk,
input rst,

output reg [3:0] count

);

always @(posedge clk or posedge rst) begin

if (rst)

count = 4'b0000;

else begin

if(count == 4'b1010)

count <= 4'b0000;

else 

count <= count + 1;

end 

end 

endmodule

07_Counters/062_Mod_10_Counter/tb_mod10_counter.v
module tb_mod10_counter;

reg clk;
reg rst;

wire [3:0]count;

mod10_counter DUT(.clk(clk), .rst(rst), .count(count));

initial clk = 0;
always #5 clk = ~clk;

always @(posedge clk or negedge clk) begin

if(clk)

$display ("\nTime = %0t: Rising Ege", $time);

else

$display ("\nTime = %0t: Falling Edge", $time);

end


initial begin

$dumpfile ("mod10_counter.vcd");
$dumpvars (0, tb_mod10_counter);

$monitor ("Time = %0t | clk = %b | rst = %b | count = %b|", $time , clk, rst, count);

rst = 1;

#10

rst = 0;


#200;
$finish;

end

endmodule

07_Counters/062_Mod_10_Counter/mod10_counter.vcd
$date
	Sat Jul  4 04:47:32 2026
$end
$version
	Icarus Verilog
$end
$timescale
	1s
$end
$scope module tb_mod10_counter $end
$var wire 4 ! count [3:0] $end
$var reg 1 " clk $end
$var reg 1 # rst $end
$scope module DUT $end
$var wire 1 " clk $end
$var wire 1 # rst $end
$var reg 4 $ count [3:0] $end
$upscope $end
$upscope $end
$enddefinitions $end
$comment Show the parameter values. $end
$dumpall
$end
#0
$dumpvars
b0 $
1#
0"
b0 !
$end
#5
1"
#10
0"
0#
#15
b1 !
b1 $
1"
#20
0"
#25
b10 !
b10 $
1"
#30
0"
#35
b11 !
b11 $
1"
#40
0"
#45
b100 !
b100 $
1"
#50
0"
#55
b101 !
b101 $
1"
#60
0"
#65
b110 !
b110 $
1"
#70
0"
#75
b111 !
b111 $
1"
#80
0"
#85
b1000 !
b1000 $
1"
#90
0"
#95
b1001 !
b1001 $
1"
#100
0"
#105
b1010 !
b1010 $
1"
#110
0"
#115
b0 !
b0 $
1"
#120
0"
#125
b1 !
b1 $
1"
#130
0"
#135
b10 !
b10 $
1"
#140
0"
#145
b11 !
b11 $
1"
#150
0"
#155
b100 !
b100 $
1"
#160
0"
#165
b101 !
b101 $
1"
#170
0"
#175
b110 !
b110 $
1"
#180
0"
#185
b111 !
b111 $
1"
#190
0"
#195
b1000 !
b1000 $
1"
#200
0"
#205
b1001 !
b1001 $
1"
